Workbook

Sheet Detail1
A1: Details for Sum of Profit - Product_Category: Accessories
A3: Transaction_ID | B3: Date | C3: Store_ID | D3: State | E3: Channel | F3: Product_Category | G3: Product | H3: Customer_ID | I3: Customer_Type | J3: Units | K3: Unit_Price_NGN | L3: Discount_Pct | M3: Revenue_Reported_NGN | N3: Cost_Per_Unit_NGN | O3: Return_Flag | P3: Sales_Rep | Q3: Corrected Revenue | R3: Profit | S3: s
A4: 100186 | B4: 46041 | C4: AB-02 | D4: Abuja | E4: Online | F4: Accessories | G4: Phone Case | H4: C1014 | I4: New | J4: 2 | K4: 9000 | L4: 0.05 | M4: 17100 | N4: 3500 | O4: No | P4: Grace | Q4: 17100 | R4: 10100
A5: 100116 | B5: 46056 | C5: PH-01 | D5: Port Harcourt | E5: In-store | F5: Accessories | G5: Backpack | H5: C1190 | I5: Returning | J5: 5 | K5: 28000 | L5: 0 | M5: 140000 | N5: 16000 | O5: No | P5: Kemi | Q5: 140000 | R5: 60000

Sheet Sheet3
A3: Row Labels | B3: Sum of Profit | K3: Row Labels | L3: Count of Transaction_ID | V3: Row Labels | W3: Average of Profit_Margin | AI3: Row Labels | AJ3: Sum of Corrected Revenue
A4: Abuja | B4: 1698100 | K4: No | L4: 384 | V4: 0 | W4: 0.40604913 | AI4: Jan | AJ4: 6722250
A5: Ibadan | B5: 2730325 | K5: Accessories | L5: 104 | V5: 0.05 | W5: 0.40257022 | AI5: Feb | AJ5: 5364300
A6: Kano | B6: 3243600 | K6: Electronics | L6: 156 | V6: 0.1 | W6: 0.36105089 | AI6: Mar | AJ6: 6298725
A7: Lagos | B7: 4579900 | K7: Home | L7: 124 | V7: 0.15 | W7: 0.33458821 | AI7: Apr | AJ7: 6343000
A8: Port Harcourt | B8: 2338500 | K8: Yes | L8: 36 | V8: 0.2 | W8: 0.2338285 | AI8: May | AJ8: 7008500
A9: Grand Total | B9: 14590425 | K9: Accessories | L9: 5 | V9: 0.25 | W9: 0.23419324 | AI9: Jun | AJ9: 5397250
K10: Electronics | L10: 21 | V10: Grand Total | W10: 0.36867966 | AI10: Jul | AJ10: 6378275
K11: Home | L11: 10 | AI11: Aug | AJ11: 3167425
K12: Grand Total | L12: 420 | AI12: Grand Total | AJ12: 46679725
A19: Row Labels | B19: Sum of Profit
A20: Accessories | B20: 1929625 | J20: Row Labels | K20: Sum of Profit | T20: Row Labels | U20: Count of Return_Flag | AD20: Row Labels | AE20: Sum of Profit
A21: Electronics | B21: 8986500 | J21: 0 | K21: 5638000 | T21: No | U21: 384 | AD21: Abuja | AE21: 1698100
A22: Home | B22: 3674300 | J22: 0.05 | K22: 4133300 | T22: In-store | U22: 189 | AD22: Ibadan | AE22: 2730325
A23: Grand Total | B23: 14590425 | J23: 0.1 | K23: 2827200 | T23: Online | U23: 121 | AD23: Kano | AE23: 3243600
J24: 0.15 | K24: 1516625 | T24: WhatsApp | U24: 74 | AD24: Lagos | AE24: 4579900 | AO24: Discount | AP24: Profit_Margin
J25: 0.2 | K25: 158700 | T25: Yes | U25: 36 | AD25: Port Harcourt | AE25: 2338500 | AO25: 0 | AP25: =SUMIFS(Cleaned_data!$R:$R,Cleaned_data!$L:$L,AO25)/SUMIFS(Cleaned_data!$Q:$Q,Cleaned_data!$L:$L,AO25) -> 0.35689191
J26: 0.25 | K26: 316600 | T26: In-store | U26: 13 | AD26: Grand Total | AE26: 14590425 | AO26: 0.05 | AP26: =SUMIFS(Cleaned_data!$R:$R,Cleaned_data!$L:$L,AO26)/SUMIFS(Cleaned_data!$Q:$Q,Cleaned_data!$L:$L,AO26) -> 0.33005933
J27: Grand Total | K27: 14590425 | T27: Online | U27: 13 | AO27: 0.1 | AP27: =SUMIFS(Cleaned_data!$R:$R,Cleaned_data!$L:$L,AO27)/SUMIFS(Cleaned_data!$Q:$Q,Cleaned_data!$L:$L,AO27) -> 0.28448952
T28: WhatsApp | U28: 10 | AO28: 0.15 | AP28: =SUMIFS(Cleaned_data!$R:$R,Cleaned_data!$L:$L,AO28)/SUMIFS(Cleaned_data!$Q:$Q,Cleaned_data!$L:$L,AO28) -> 0.2713917
T29: Grand Total | U29: 420 | AO29: 0.2 | AP29: =SUMIFS(Cleaned_data!$R:$R,Cleaned_data!$L:$L,AO29)/SUMIFS(Cleaned_data!$Q:$Q,Cleaned_data!$L:$L,AO29) -> 0.20794025
AO30: 0.25 | AP30: =SUMIFS(Cleaned_data!$R:$R,Cleaned_data!$L:$L,AO30)/SUMIFS(Cleaned_data!$Q:$Q,Cleaned_data!$L:$L,AO30) -> 0.15294686
AO35: Discount | AP35: Average Profit Margin
AO36: 0 | AP36: 0.417
AO37: 0.05 | AP37: 0.39
T38: Row Labels | U38: Sum of Corrected Revenue | AO38: 0.1 | AP38: 0.364
T39: Jan | U39: 6722250 | AO39: 0.15 | AP39: 0.333
D40: Row Labels | E40: Sum of Profit | T40: Feb | U40: 5364300 | AO40: 0.2 | AP40: 0.208
D41: Accessories | E41: 1929625 | T41: Mar | U41: 6298725 | AO41: 0.25 | AP41: 0.163
D42: Electronics | E42: 8986500 | T42: Apr | U42: 6343000
D43: Home | E43: 3674300 | T43: May | U43: 7008500
D44: Grand Total | E44: 14590425 | T44: Jun | U44: 5397250
T45: Jul | U45: 6378275
T46: Aug | U46: 3167425
T47: Grand Total | U47: 46679725
A63: Row Labels | B63: Count of Return_Flag
A64: No | B64: 384
A65: In-store | B65: 189
A66: Online | B66: 121
A67: WhatsApp | B67: 74 | Q67: Channel | R67: Return Rate
A68: Yes | B68: 36 | Q68: In-store | R68: 0.0644
A69: In-store | B69: 13 | Q69: Online | R69: 0.097
A70: Online | B70: 13 | Q70: WhatsApp | R70: 0.119
A71: WhatsApp | B71: 10
A72: Grand Total | B72: 420

Sheet Dashboard
A1: {=A1=A1:EB273} -> 0
C9: z
BL177: z

Sheet Sheet1

Sheet Cleaned_data
A1: Transaction_ID | B1: Date | C1: Store_ID | D1: State | E1: Channel | F1: Product_Category | G1: Product | H1: Customer_ID | I1: Customer_Type | J1: Units | K1: Unit_Price_NGN | L1: Discount_Pct | M1: Revenue_Reported_NGN | N1: Cost_Per_Unit_NGN | O1: Return_Flag | P1: Sales_Rep | Q1: Corrected Revenue | R1: Profit | S1: Revenue_Check | T1: Profit_Margin
A2: 100001 | B2: 46167 | C2: AB-02 | D2: Abuja | E2: WhatsApp | F2: Home | G2: Standing Fan | H2: C1141 | I2: New | J2: 1 | K2: 58000 | L2: 0 | M2: 58000 | N2: 39000 | O2: No | P2: Chinedu | Q2: =J2*K2*(1-L2) -> 58000 | R2: =Q2-(J2*N2) -> 19000 | S2: =IF(M2=Q2,"Match","Mismatch") -> Match | T2: =R2/Q2 -> 0.32758621
A3: 100002 | B3: 46129 | C3: LG-01 | D3: Lagos | E3: WhatsApp | F3: Electronics | G3: Smartphone | H3: C1083 | I3: Returning | J3: 5 | K3: 165000 | L3: 0.05 | M3: 627000 | N3: 112000 | O3: No | P3: Kemi | Q3: =J3*K3*(1-L3) -> 783750 | R3: =Q3-(J3*N3) -> 223750 | S3: =IF(M3=Q3,"Match","Mismatch") -> Mismatch | T3: =R3/Q3 -> 0.28548644
A4: 100003 | B4: 46079 | C4: AB-01 | D4: Abuja | E4: WhatsApp | F4: Electronics | G4: Earbuds | H4: C1029 | I4: Returning | J4: 3 | K4: 32000 | L4: 0.2 | M4: 76800 | N4: 19000 | O4: No | P4: Chinedu | Q4: =J4*K4*(1-L4) -> 76800 | R4: =Q4-(J4*N4) -> 19800 | S4: =IF(M4=Q4,"Match","Mismatch") -> Match | T4: =R4/Q4 -> 0.2578125
A5: 100004 | B5: 46182 | C5: KN-01 | D5: Kano | E5: Online | F5: Electronics | G5: Power Bank | H5: C1082 | I5: Returning | J5: 4 | K5: 26000 | L5: 0 | M5: 104000 | N5: 15000 | O5: No | P5: Grace | Q5: =J5*K5*(1-L5) -> 104000 | R5: =Q5-(J5*N5) -> 44000 | S5: =IF(M5=Q5,"Match","Mismatch") -> Match | T5: =R5/Q5 -> 0.42307692
A6: 100005 | B6: 46172 | C6: LG-01 | D6: Lagos | E6: Online | F6: Electronics | G6: Smartphone | H6: C1180 | I6: Returning | J6: 1 | K6: 165000 | L6: 0.05 | M6: 156750 | N6: 112000 | O6: No | P6: Chinedu | Q6: =J6*K6*(1-L6) -> 156750 | R6: =Q6-(J6*N6) -> 44750 | S6: =IF(M6=Q6,"Match","Mismatch") -> Match | T6: =R6/Q6 -> 0.28548644
A7: 100006 | B7: 46238 | C7: LG-02 | D7: Lagos | E7: In-store | F7: Accessories | G7: USB Cable | H7: C1161 | I7: Returning | J7: 3 | K7: 6500 | L7: 0.1 | M7: 17550 | N7: 2200 | O7: No | P7: Bola | Q7: =J7*K7*(1-L7) -> 17550 | R7: =Q7-(J7*N7) -> 10950 | S7: =IF(M7=Q7,"Match","Mismatch") -> Match | T7: =R7/Q7 -> 0.62393162
A8: 100007 | B8: 46090 | C8: LG-01 | D8: Lagos | E8: In-store | F8: Electronics | G8: Power Bank | H8: C1007 | I8: New | J8: 3 | K8: 26000 | L8: 0.1 | M8: 70200 | N8: 15000 | O8: No | P8: Chinedu | Q8: =J8*K8*(1-L8) -> 70200 | R8: =Q8-(J8*N8) -> 25200 | S8: =IF(M8=Q8,"Match","Mismatch") -> Match | T8: =R8/Q8 -> 0.35897436
A9: 100008 | B9: 46229 | C9: KN-01 | D9: Kano | E9: Online | F9: Electronics | G9: Smartphone | H9: C1051 | I9: Returning | J9: 5 | K9: 165000 | L9: 0.05 | M9: 783750 | N9: 112000 | O9: No | P9: Kemi | Q9: =J9*K9*(1-L9) -> 783750 | R9: =Q9-(J9*N9) -> 223750 | S9: =IF(M9=Q9,"Match","Mismatch") -> Match | T9: =R9/Q9 -> 0.28548644
A10: 100009 | B10: 46028 | C10: IB-01 | D10: Ibadan | E10: In-store | F10: Home | G10: Blender | H10: C1111 | I10: Returning | J10: 3 | K10: 42000 | L10: 0.15 | M10: 107100 | N10: 28000 | O10: No | P10: Fatima | Q10: =J10*K10*(1-L10) -> 107100 | R10: =Q10-(J10*N10) -> 23100 | S10: =IF(M10=Q10,"Match","Mismatch") -> Match | T10: =R10/Q10 -> 0.21568627
A11: 100010 | B11: 46248 | C11: PH-01 | D11: Port Harcourt | E11: In-store | F11: Electronics | G11: Smartphone | H11: C1153 | I11: Returning | J11: 1 | K11: 165000 | L11: 0 | M11: 165000 | N11: 112000 | O11: No | P11: David | Q11: =J11*K11*(1-L11) -> 165000 | R11: =Q11-(J11*N11) -> 53000 | S11: =IF(M11=Q11,"Match","Mismatch") -> Match | T11: =R11/Q11 -> 0.32121212
A12: 100011 | B12: 46200 | C12: LG-01 | D12: Lagos | E12: In-store | F12: Electronics | G12: Earbuds | H12: C1059 | I12: Returning | J12: 1 | K12: 32000 | L12: 0 | M12: 32000 | N12: 19000 | O12: No | P12: David | Q12: =J12*K12*(1-L12) -> 32000 | R12: =Q12-(J12*N12) -> 13000 | S12: =IF(M12=Q12,"Match","Mismatch") -> Match | T12: =R12/Q12 -> 0.40625
A13: 100012 | B13: 46120 | C13: KN-01 | D13: Kano | E13: Online | F13: Accessories | G13: Phone Case | H13: C1028 | I13: New | J13: 1 | K13: 9000 | L13: 0 | M13: 9000 | N13: 3500 | O13: No | P13: David | Q13: =J13*K13*(1-L13) -> 9000 | R13: =Q13-(J13*N13) -> 5500 | S13: =IF(M13=Q13,"Match","Mismatch") -> Match | T13: =R13/Q13 -> 0.61111111
... A421: 100420 | B421: 46079 | C421: KN-01 | D421: Kano | E421: WhatsApp | F421: Electronics | G421: Smartphone | H421: C1089 | I421: Returning | J421: 2 | K421: 165000 | L421: 0.05 | M421: 313500 | N421: 112000 | O421: No | P421: Ibrahim | Q421: =J421*K421*(1-L421) -> 313500 | R421: =Q421-(J421*N421) -> 89500 | S421: =IF(M421=Q421,"Match","Mismatch") -> Match | T421: =R421/Q421 -> 0.28548644

Sheet Duplicate Check
A1: Transaction_ID | B1: Date | C1: Store_ID | D1: State | E1: Channel | F1: Product_Category | G1: Product | H1: Customer_ID | I1: Customer_Type | J1: Units | K1: Unit_Price_NGN | L1: Discount_Pct | M1: Revenue_Reported_NGN | N1: Cost_Per_Unit_NGN | O1: Return_Flag | P1: Sales_Rep
A2: 100001 | B2: 46167 | C2: AB-02 | D2: Abuja | E2: WhatsApp | F2: Home | G2: Standing Fan | H2: C1141 | I2: New | J2: 1 | K2: 58000 | L2: 0 | M2: 58000 | O2: No | P2: Chinedu
A3: 100002 | B3: 46129 | C3: LG-01 | D3: Lagos | E3: WhatsApp | F3: Electronics | G3: Smartphone | H3: C1083 | I3: Returning | J3: 5 | K3: 165000 | L3: 0.05 | M3: 627000 | N3: 112000 | O3: No | P3: Kemi
A4: 100003 | B4: 46079 | C4: AB-01 | D4: Abuja | E4: WhatsApp | F4: Electronics | G4: Earbuds | H4: C1029 | I4: Returning | J4: 3 | K4: 32000 | L4: 0.2 | M4: 76800 | N4: 19000 | O4: No | P4: Chinedu
A5: 100004 | B5: 46182 | C5: KN-01 | D5: Kano | E5: Online | F5: Electronics | G5: Power Bank | H5: C1082 | I5: Returning | J5: 4 | K5: 26000 | L5: 0 | M5: 104000 | N5: 15000 | O5: No | P5: Grace
A6: 100005 | B6: 46172 | C6: LG-01 | D6: Lagos | E6: Online | F6: Electronics | G6: Smartphone | H6: C1180 | I6: Returning | J6: 1 | K6: 165000 | L6: 0.05 | M6: 156750 | N6: 112000 | O6: No | P6: Chinedu
A7: 100006 | B7: 46238 | C7: LG-02 | D7: Lagos | E7: In-store | F7: Accessories | G7: USB Cable | H7: C1161 | I7: Returning | J7: 3 | K7: 6500 | L7: 0.1 | M7: 17550 | N7: 2200 | O7: No | P7: Bola
A8: 100007 | B8: 46090 | C8: LG-01 | D8: Lagos | E8: In-store | F8: Electronics | G8: Power Bank | H8: C1007 | I8: New | J8: 3 | K8: 26000 | L8: 0.1 | M8: 70200 | N8: 15000 | O8: No | P8: Chinedu
A9: 100008 | B9: 46229 | C9: KN-01 | D9: Kano | E9: Online | F9: Electronics | G9: Smartphone | H9: C1051 | I9: Returning | J9: 5 | K9: 165000 | L9: 0.05 | M9: 783750 | N9: 112000 | O9: No | P9: Kemi
A10: 100009 | B10: 46028 | C10: IB-01 | D10: Ibadan | E10: In-store | F10: Home | G10: Blender | H10: C1111 | I10: Returning | J10: 3 | K10: 42000 | L10: 0.15 | M10: 107100 | N10: 28000 | O10: No | P10: Fatima
A11: 100010 | B11: 46248 | C11: PH-01 | D11: Port Harcourt | E11: In-store | F11: Electronics | G11: Smartphone | H11: C1153 | I11: Returning | J11: 1 | K11: 165000 | L11: 0 | M11: 165000 | N11: 112000 | O11: No | P11: David
A12: 100011 | B12: 46200 | C12: LG-01 | D12: Lagos | E12: In-store | F12: Electronics | G12: Earbuds | H12: C1059 | I12: Returning | J12: 1 | K12: 32000 | L12: 0 | M12: 32000 | N12: 19000 | O12: No | P12: David
A13: 100012 | B13: 46120 | C13: KN-01 | D13: Kano | E13: Online | F13: Accessories | G13: Phone Case | H13: C1028 | I13: New | J13: 1 | K13: 9000 | L13: 0 | M13: 9000 | N13: 3500 | O13: No | P13: David
A14: 100013 | B14: 46153 | C14: IB-01 | D14: Ibadan | E14: In-store | F14: Home | G14: Electric Kettle | H14: C1192 | I14: New | J14: 2 | K14: 24000 | L14: 0 | M14: 48000 | N14: 15000 | O14: No | P14: Ibrahim
A15: 100014 | B15: 46195 | C15: AB-02 | D15: Abuja | E15: WhatsApp | F15: Accessories | G15: Backpack | H15: C1022 | I15: Returning | J15: 2 | K15: 28000 | L15: 0.25 | M15: 42000 | O15: No | P15: Fatima
A16: 100015 | B16: 46031 | C16: PH-01 | D16: Port Harcourt | E16: In-store | F16: Electronics | G16: Smartphone | H16: C1084 | I16: New | J16: 2 | K16: 165000 | L16: 0 | M16: 330000 | N16: 112000 | O16: No | P16: Grace
A17: 100016 | B17: 46228 | C17: LG-02 | D17: Lagos | E17: Online | F17: Accessories | G17: USB Cable | H17: C1123 | I17: New | J17: 1 | K17: 6500 | L17: 0.1 | M17: 4680 | N17: 2200 | O17: No | P17: Kemi
A18: 100017 | B18: 46032 | C18: KN-01 | D18: Kano | E18: WhatsApp | F18: Home | G18: Blender | H18: C1134 | I18: New | J18: 2 | K18: 42000 | L18: 0 | M18: 84000 | N18: 28000 | O18: No | P18: Ibrahim
A19: 100018 | B19: 46141 | C19: PH-01 | D19: Port Harcourt | E19: In-store | F19: Accessories | G19: USB Cable | H19: C1100 | I19: Returning | J19: 22 | K19: 6500 | L19: 0.15 | M19: 121550 | N19: 2200 | O19: No | P19: Kemi
A20: 100019 | B20: 46148 | C20: LG-01 | D20: Lagos | E20: In-store | F20: Electronics | G20: Power Bank | H20: C1189 | I20: Returning | J20: 1 | K20: 26000 | L20: 0.15 | M20: 22100 | N20: 15000 | O20: No | P20: Bola
A21: 100020 | B21: 46131 | C21: AB-02 | D21: Abuja | E21: In-store | F21: Electronics | G21: Power Bank | H21: C1050 | I21: Returning | J21: 1 | K21: 26000 | L21: 0.25 | M21: 19500 | O21: No | P21: Ibrahim
A22: 100021 | B22: 46148 | C22: AB-02 | D22: Abuja | E22: WhatsApp | F22: Electronics | G22: Power Bank | H22: C1184 | I22: New | J22: 1 | K22: 26000 | L22: 0 | M22: 26000 | N22: 15000 | O22: No | P22: Kemi
A23: 100022 | B23: 46033 | C23: IB-01 | D23: Ibadan | E23: WhatsApp | F23: Accessories | G23: Backpack | H23: C1022 | I23: New | J23: 1 | K23: 28000 | L23: 0.05 | M23: 26600 | N23: 16000 | O23: No | P23: Bola
A24: 100023 | B24: 46052 | C24: AB-01 | D24: Abuja | E24: Online | F24: Electronics | G24: Earbuds | H24: C1004 | I24: Returning | J24: 1 | K24: 32000 | L24: 0.15 | M24: 27200 | N24: 19000 | O24: No | P24: David
A25: 100024 | B25: 46150 | C25: AB-01 | D25: Abuja | E25: In-store | F25: Home | G25: Standing Fan | H25: C1034 | I25: New | J25: 2 | K25: 58000 | L25: 0.2 | M25: 92800 | O25: Yes | P25: Grace
A26: 100025 | B26: 46027 | C26: KN-01 | D26: Kano | E26: In-store | F26: Home | G26: Standing Fan | H26: C1164 | I26: Returning | J26: 5 | K26: 58000 | L26: 0.05 | M26: 275500 | N26: 39000 | O26: No | P26: David
A27: 100026 | B27: 46203 | C27: IB-01 | D27: Ibadan | E27: In-store | F27: Accessories | G27: Phone Case | H27: C1155 | I27: Returning | J27: 2 | K27: 9000 | L27: 0.1 | M27: 16200 | O27: No | P27: Chinedu
A28: 100027 | B28: 46142 | C28: KN-01 | D28: Kano | E28: WhatsApp | F28: Home | G28: Standing Fan | H28: C1073 | I28: New | J28: 4 | K28: 58000 | L28: 0.05 | M28: 220400 | N28: 39000 | O28: No | P28: David
A29: 100028 | B29: 46156 | C29: AB-01 | D29: Abuja | E29: Online | F29: Electronics | G29: Power Bank | H29: C1136 | I29: Returning | J29: 22 | K29: 26000 | L29: 0.25 | M29: 429000 | N29: 15000 | O29: No | P29: Bola
A30: 100029 | B30: 46103 | C30: AB-01 | D30: Abuja | E30: In-store | F30: Home | G30: Standing Fan | H30: C1173 | I30: Returning | J30: 5 | K30: 58000 | L30: 0.1 | M30: 261000 | O30: No | P30: Chinedu
A31: 100030 | B31: 46209 | C31: KN-01 | D31: Kano | E31: Online | F31: Electronics | G31: Power Bank | H31: C1071 | I31: New | J31: 1 | K31: 26000 | L31: 0.05 | M31: 24700 | N31: 15000 | O31: No | P31: David
A32: 100031 | B32: 46182 | C32: AB-01 | D32: Abuja | E32: In-store | F32: Home | G32: Standing Fan | H32: C1047 | I32: New | J32: 2 | K32: 58000 | L32: 0.15 | M32: 98600 | N32: 39000 | O32: No | P32: Aisha
A33: 100032 | B33: 46109 | C33: PH-01 | D33: Port Harcourt | E33: Online | F33: Home | G33: Electric Kettle | H33: C1051 | I33: New | J33: 1 | K33: 24000 | L33: 0.05 | M33: 22800 | N33: 15000 | O33: No | P33: Kemi
A34: 100033 | B34: 46152 | C34: LG-01 | D34: Lagos | E34: In-store | F34: Home | G34: Standing Fan | H34: C1094 | I34: New | J34: 3 | K34: 58000 | L34: 0 | M34: 174000 | N34: 39000 | O34: No | P34: Aisha
A35: 100034 | B35: 46157 | C35: PH-01 | D35: Port Harcourt | E35: In-store | F35: Home | G35: Standing Fan | H35: C1089 | I35: Returning | J35: 1 | K35: 58000 | L35: 0.15 | M35: 49300 | N35: 39000 | O35: No | P35: Bola
A36: 100035 | B36: 46076 | C36: KN-01 | D36: Kano | E36: In-store | F36: Accessories | G36: Backpack | H36: C1048 | I36: Returning | J36: 25 | K36: 28000 | L36: 0.05 | M36: 665000 | N36: 16000 | O36: No | P36: Ibrahim
A37: 100036 | B37: 46076 | C37: KN-01 | D37: Kano | E37: In-store | F37: Electronics | G37: Earbuds | H37: C1056 | I37: New | J37: 2 | K37: 32000 | L37: 0.05 | M37: 60800 | N37: 19000 | O37: Yes | P37: Bola
A38: 100037 | B38: 46124 | C38: AB-01 | D38: Abuja | E38: In-store | F38: Accessories | G38: Backpack | H38: C1036 | I38: New | J38: 2 | K38: 28000 | L38: 0 | M38: 56000 | N38: 16000 | O38: No | P38: Grace
A39: 100038 | B39: 46037 | C39: KN-01 | D39: Kano | E39: Online | F39: Electronics | G39: Earbuds | H39: C1138 | I39: Returning | J39: 2 | K39: 32000 | L39: 0 | M39: 64000 | N39: 19000 | O39: No | P39: Aisha
A40: 100039 | B40: 46116 | C40: AB-02 | D40: Abuja | E40: Online | F40: Accessories | G40: USB Cable | H40: C1044 | I40: New | J40: 3 | K40: 6500 | L40: 0.1 | M40: 17550 | N40: 2200 | O40: No | P40: Grace
A41: 100040 | B41: 46145 | C41: AB-01 | D41: Abuja | E41: WhatsApp | F41: Home | G41: Standing Fan | H41: C1063 | I41: Returning | J41: 1 | K41: 58000 | L41: 0.05 | M41: 55100 | N41: 39000 | O41: No | P41: Kemi
A42: 100041 | B42: 46035 | C42: PH-01 | D42: Port Harcourt | E42: WhatsApp | F42: Electronics | G42: Earbuds | H42: C1001 | I42: Returning | J42: 3 | K42: 32000 | L42: 0.1 | M42: 86400 | N42: 19000 | O42: No | P42: Bola
... A51: 100050 | B51: 46056 | C51: KN-01 | D51: Kano | E51: In-store | F51: Accessories | G51: Phone Case | H51: C1080 | I51: Returning | J51: 3 | K51: 9000 | L51: 0 | M51: 27000 | N51: 3500 | O51: No | P51: Chinedu
A52: 100051 | B52: 46035 | C52: AB-02 | D52: Abuja | E52: Online | F52: Home | G52: Blender | H52: C1111 | I52: New | J52: 2 | K52: 42000 | L52: 0.1 | M52: 75600 | O52: No | P52: Chinedu
A53: 100052 | B53: 46033 | C53: PH-01 | D53: Port Harcourt | E53: WhatsApp | F53: Electronics | G53: Smartphone | H53: C1005 | I53: Returning | J53: 4 | K53: 165000 | L53: 0 | M53: 660000 | N53: 112000 | O53: No | P53: Chinedu
A54: 100053 | B54: 46180 | C54: KN-01 | D54: Kano | E54: In-store | F54: Accessories | G54: USB Cable | H54: C1193 | I54: Returning | J54: 4 | K54: 6500 | L54: 0 | M54: 26000 | N54: 2200 | O54: No | P54: Ibrahim
A55: 100054 | B55: 46140 | C55: AB-01 | D55: Abuja | E55: In-store | F55: Accessories | G55: Phone Case | H55: C1030 | I55: Returning | J55: 1 | K55: 9000 | L55: 0.1 | M55: 8100 | N55: 3500 | O55: No | P55: Aisha
A56: 100055 | B56: 46178 | C56: KN-01 | D56: Kano | E56: In-store | F56: Electronics | G56: Power Bank | H56: C1019 | I56: New | J56: 2 | K56: 26000 | L56: 0.15 | M56: 44200 | N56: 15000 | O56: No | P56: Bola
A57: 100056 | B57: 46191 | C57: KN-01 | D57: Kano | E57: In-store | F57: Accessories | G57: Phone Case | H57: C1187 | I57: New | J57: 1 | K57: 9000 | L57: 0.05 | M57: 6840 | N57: 3500 | O57: No | P57: Bola
A58: 100057 | B58: 46196 | C58: IB-01 | D58: Ibadan | E58: Online | F58: Electronics | G58: Power Bank | H58: C1190 | I58: New | J58: 1 | K58: 26000 | L58: 0.15 | M58: 22100 | N58: 15000 | O58: No | P58: Fatima
A59: 100058 | B59: 46140 | C59: KN-01 | D59: Kano | E59: In-store | F59: Accessories | G59: Backpack | H59: C1069 | I59: Returning | J59: 2 | K59: 28000 | L59: 0 | M59: 56000 | N59: 16000 | O59: No | P59: Aisha
A60: 100059 | B60: 46039 | C60: LG-02 | D60: Lagos | E60: Online | F60: Home | G60: Blender | H60: C1074 | I60: Returning | J60: 2 | K60: 42000 | L60: 0.1 | M60: 75600 | N60: 28000 | O60: No | P60: Aisha
A61: 100060 | B61: 46046 | C61: IB-01 | D61: Ibadan | E61: Online | F61: Electronics | G61: Earbuds | H61: C1156 | I61: Returning | J61: 1 | K61: 32000 | L61: 0.1 | M61: 28800 | N61: 19000 | O61: No | P61: Bola
A62: 100061 | B62: 46251 | C62: LG-02 | D62: Lagos | E62: In-store | F62: Electronics | G62: Earbuds | H62: C1039 | I62: Returning | J62: 1 | K62: 32000 | L62: 0.15 | M62: 27200 | N62: 19000 | O62: No | P62: Aisha
A63: 100062 | B63: 46161 | C63: PH-01 | D63: Port Harcourt | E63: Online | F63: Electronics | G63: Smartphone | H63: C1045 | I63: New | J63: 3 | K63: 165000 | L63: 0 | M63: 495000 | N63: 112000 | O63: No | P63: Aisha | Q63: =COUNTIF(A:A,A75) -> 1
A64: 100063 | B64: 46114 | C64: LG-02 | D64: Lagos | E64: In-store | F64: Home | G64: Standing Fan | H64: C1164 | I64: New | J64: 1 | K64: 58000 | L64: 0 | M64: 58000 | N64: 39000 | O64: No | P64: Fatima
A65: 100064 | B65: 46224 | C65: LG-01 | D65: Lagos | E65: WhatsApp | F65: Home | G65: Electric Kettle | H65: C1179 | I65: New | J65: 1 | K65: 24000 | L65: 0.05 | M65: 22800 | N65: 15000 | O65: No | P65: Kemi
A66: 100065 | B66: 46172 | C66: PH-01 | D66: Port Harcourt | E66: In-store | F66: Electronics | G66: Smartphone | H66: C1055 | I66: Returning | J66: 4 | K66: 165000 | L66: 0.1 | M66: 594000 | N66: 112000 | O66: No | P66: David
A67: 100066 | B67: 46107 | C67: IB-01 | D67: Ibadan | E67: Online | F67: Home | G67: Blender | H67: C1106 | I67: Returning | J67: 3 | K67: 42000 | L67: 0.1 | M67: 113400 | N67: 28000 | O67: No | P67: Kemi
A68: 100067 | B68: 46210 | C68: AB-02 | D68: Abuja | E68: WhatsApp | F68: Accessories | G68: Backpack | H68: C1157 | I68: New | J68: 3 | K68: 28000 | L68: 0.15 | M68: 57120 | N68: 16000 | O68: No | P68: David
A69: 100068 | B69: 46111 | C69: AB-02 | D69: Abuja | E69: Online | F69: Accessories | G69: Backpack | H69: C1000 | I69: New | J69: 4 | K69: 28000 | L69: 0.05 | M69: 106400 | N69: 16000 | O69: No | P69: David
A70: 100069 | B70: 46092 | C70: PH-01 | D70: Port Harcourt | E70: In-store | F70: Electronics | G70: Smartphone | H70: C1032 | I70: New | J70: 3 | K70: 165000 | L70: 0.05 | M70: 470250 | N70: 112000 | O70: No | P70: Bola
A71: 100070 | B71: 46147 | C71: PH-01 | D71: Port Harcourt | E71: In-store | F71: Home | G71: Standing Fan | H71: C1024 | I71: New | J71: 3 | K71: 58000 | L71: 0 | M71: 174000 | O71: No | P71: Ibrahim
A72: 100071 | B72: 46028 | C72: LG-02 | D72: Lagos | E72: Online | F72: Electronics | G72: Power Bank | H72: C1018 | I72: Returning | J72: 4 | K72: 26000 | L72: 0.1 | M72: 93600 | N72: 15000 | O72: No | P72: Chinedu
A73: 100072 | B73: 46182 | C73: IB-01 | D73: Ibadan | E73: In-store | F73: Home | G73: Standing Fan | H73: C1058 | I73: New | J73: 3 | K73: 58000 | L73: 0.1 | M73: 125280 | N73: 39000 | O73: No | P73: Grace
A74: 100073 | B74: 46086 | C74: AB-01 | D74: Abuja | E74: Online | F74: Electronics | G74: Power Bank | H74: C1086 | I74: Returning | J74: 1 | K74: 26000 | L74: 0.1 | M74: 23400 | N74: 15000 | O74: Yes | P74: Bola
A75: 100074 | B75: 46132 | C75: IB-01 | D75: Ibadan | E75: In-store | F75: Accessories | G75: USB Cable | H75: C1043 | I75: New | J75: 4 | K75: 6500 | L75: 0.05 | M75: 24700 | N75: 2200 | O75: No | P75: Chinedu
A76: 100075 | B76: 46256 | C76: LG-01 | D76: Lagos | E76: In-store | F76: Electronics | G76: Smartphone | H76: C1188 | I76: Returning | J76: 1 | K76: 165000 | L76: 0.05 | M76: 156750 | N76: 112000 | O76: No | P76: Fatima
A77: 100076 | B77: 46064 | C77: LG-01 | D77: Lagos | E77: In-store | F77: Electronics | G77: Power Bank | H77: C1104 | I77: New | J77: 4 | K77: 26000 | L77: 0 | M77: 104000 | N77: 15000 | O77: No | P77: Aisha
A78: 100077 | B78: 46156 | C78: LG-02 | D78: Lagos | E78: In-store | F78: Accessories | G78: Phone Case | H78: C1192 | I78: New | J78: 2 | K78: 9000 | L78: 0.15 | M78: 15300 | N78: 3500 | O78: No | P78: Chinedu
A79: 100078 | B79: 46209 | C79: LG-01 | D79: Lagos | E79: In-store | F79: Accessories | G79: USB Cable | H79: C1108 | I79: Returning | J79: 2 | K79: 6500 | L79: 0.1 | M79: 11700 | N79: 2200 | O79: No | P79: Kemi
A80: 100079 | B80: 46058 | C80: LG-02 | D80: Lagos | E80: In-store | F80: Home | G80: Standing Fan | H80: C1159 | I80: Returning | J80: 2 | K80: 58000 | L80: 0.1 | M80: 104400 | N80: 39000 | O80: No | P80: Aisha
A81: 100080 | B81: 46255 | C81: IB-01 | D81: Ibadan | E81: Online | F81: Accessories | G81: Backpack | H81: C1017 | I81: Returning | J81: 2 | K81: 28000 | L81: 0.1 | M81: 50400 | N81: 16000 | O81: No | P81: Kemi
A82: 100081 | B82: 46151 | C82: LG-02 | D82: Lagos | E82: Online | F82: Electronics | G82: Earbuds | H82: C1143 | I82: New | J82: 2 | K82: 32000 | L82: 0 | M82: 64000 | N82: 19000 | O82: No | P82: Aisha
A83: 100082 | B83: 46149 | C83: AB-01 | D83: Abuja | E83: Online | F83: Electronics | G83: Smartphone | H83: C1089 | I83: New | J83: 2 | K83: 165000 | L83: 0.1 | M83: 297000 | O83: No | P83: Fatima
A84: 100083 | B84: 46079 | C84: LG-02 | D84: Lagos | E84: In-store | F84: Electronics | G84: Smartphone | H84: C1133 | I84: Returning | J84: 3 | K84: 165000 | L84: 0.1 | M84: 445500 | N84: 112000 | O84: Yes | P84: Fatima
A85: 100084 | B85: 46226 | C85: AB-01 | D85: Abuja | E85: In-store | F85: Electronics | G85: Power Bank | H85: C1097 | I85: New | J85: 4 | K85: 26000 | L85: 0 | M85: 104000 | N85: 15000 | O85: Yes | P85: Kemi
A86: 100085 | B86: 46227 | C86: PH-01 | D86: Port Harcourt | E86: WhatsApp | F86: Electronics | G86: Power Bank | H86: C1020 | I86: Returning | J86: 3 | K86: 26000 | L86: 0 | M86: 78000 | N86: 15000 | O86: No | P86: Aisha
A87: 100086 | B87: 46068 | C87: KN-01 | D87: Kano | E87: Online | F87: Electronics | G87: Earbuds | H87: C1177 | I87: Returning | J87: 4 | K87: 32000 | L87: 0.1 | M87: 115200 | N87: 19000 | O87: No | P87: Fatima
A88: 100087 | B88: 46032 | C88: AB-01 | D88: Abuja | E88: WhatsApp | F88: Accessories | G88: Backpack | H88: C1150 | I88: Returning | J88: 3 | K88: 28000 | L88: 0.15 | M88: 71400 | N88: 16000 | O88: No | P88: Fatima
A89: 100088 | B89: 46191 | C89: KN-01 | D89: Kano | E89: WhatsApp | F89: Electronics | G89: Earbuds | H89: C1128 | I89: Returning | J89: 5 | K89: 32000 | L89: 0.05 | M89: 152000 | N89: 19000 | O89: Yes | P89: Chinedu
A90: 100089 | B90: 46024 | C90: KN-01 | D90: Kano | E90: In-store | F90: Home | G90: Blender | H90: C1089 | I90: Returning | J90: 1 | K90: 42000 | L90: 0.05 | M90: 39900 | N90: 28000 | O90: No | P90: Bola
A91: 100090 | B91: 46085 | C91: KN-01 | D91: Kano | E91: Online | F91: Home | G91: Blender | H91: C1169 | I91: Returning | J91: 4 | K91: 42000 | L91: 0.05 | M91: 159600 | N91: 28000 | O91: No | P91: Kemi
A92: 100091 | B92: 46190 | C92: PH-01 | D92: Port Harcourt | E92: Online | F92: Accessories | G92: Phone Case | H92: C1166 | I92: New | J92: 2 | K92: 9000 | L92: 0.1 | M92: 16200 | N92: 3500 | O92: No | P92: Grace
A93: 100092 | B93: 46153 | C93: PH-01 | D93: Port Harcourt | E93: In-store | F93: Home | G93: Blender | H93: C1108 | I93: Returning | J93: 4 | K93: 42000 | L93: 0.1 | M93: 166320 | N93: 28000 | O93: No | P93: Bola
A94: 100093 | B94: 46139 | C94: AB-01 | D94: Abuja | E94: In-store | F94: Accessories | G94: Phone Case | H94: C1031 | I94: Returning | J94: 5 | K94: 9000 | L94: 0.2 | M94: 36000 | O94: No | P94: Fatima
A95: 100094 | B95: 46223 | C95: LG-02 | D95: Lagos | E95: In-store | F95: Home | G95: Blender | H95: C1036 | I95: Returning | J95: 4 | K95: 42000 | L95: 0.05 | M95: 127680 | N95: 28000 | O95: No | P95: Fatima
A96: 100095 | B96: 46148 | C96: LG-01 | D96: Lagos | E96: Online | F96: Accessories | G96: Phone Case | H96: C1092 | I96: New | J96: 1 | K96: 9000 | L96: 0.05 | M96: 8550 | N96: 3500 | O96: No | P96: Aisha
A97: 100096 | B97: 46049 | C97: AB-02 | D97: Abuja | E97: Online | F97: Electronics | G97: Power Bank | H97: C1038 | I97: Returning | J97: 3 | K97: 26000 | L97: 0 | M97: 78000 | O97: No | P97: David
A98: 100097 | B98: 46122 | C98: PH-01 | D98: Port Harcourt | E98: In-store | F98: Electronics | G98: Power Bank | H98: C1134 | I98: Returning | J98: 4 | K98: 26000 | L98: 0 | M98: 104000 | N98: 15000 | O98: No | P98: Bola
A99: 100098 | B99: 46074 | C99: LG-01 | D99: Lagos | E99: Online | F99: Home | G99: Blender | H99: C1071 | I99: New | J99: 1 | K99: 42000 | L99: 0.05 | M99: 39900 | N99: 28000 | O99: No | P99: Fatima
A100: 100099 | B100: 46089 | C100: LG-01 | D100: Lagos | E100: In-store | F100: Electronics | G100: Earbuds | H100: C1111 | I100: New | J100: 2 | K100: 32000 | L100: 0 | M100: 64000 | N100: 19000 | O100: No | P100: Fatima
A101: 100100 | B101: 46086 | C101: LG-02 | D101: Lagos | E101: In-store | F101: Electronics | G101: Earbuds | H101: C1048 | I101: New | J101: 3 | K101: 32000 | L101: 0.05 | M101: 91200 | N101: 19000 | O101: No | P101: Ibrahim
A102: 100101 | B102: 46213 | C102: AB-02 | D102: Abuja | E102: In-store | F102: Accessories | G102: Phone Case | H102: C1052 | I102: Returning | J102: 5 | K102: 9000 | L102: 0.05 | M102: 42750 | N102: 3500 | O102: No | P102: Chinedu
A103: 100102 | B103: 46199 | C103: LG-02 | D103: Lagos | E103: WhatsApp | F103: Home | G103: Electric Kettle | H103: C1014 | I103: Returning | J103: 2 | K103: 24000 | L103: 0 | M103: 48000 | N103: 15000 | O103: No | P103: Ibrahim
A104: 100103 | B104: 46193 | C104: AB-01 | D104: Abuja | E104: Online | F104: Electronics | G104: Smartphone | H104: C1110 | I104: New | J104: 1 | K104: 165000 | L104: 0 | M104: 165000 | N104: 112000 | O104: Yes | P104: Bola
A105: 100104 | B105: 46066 | C105: LG-01 | D105: Lagos | E105: In-store | F105: Electronics | G105: Smartphone | H105: C1167 | I105: New | J105: 3 | K105: 165000 | L105: 0 | M105: 495000 | N105: 112000 | O105: No | P105: Grace
A106: 100105 | B106: 46177 | C106: IB-01 | D106: Ibadan | E106: WhatsApp | F106: Home | G106: Standing Fan | H106: C1002 | I106: New | J106: 2 | K106: 58000 | L106: 0 | M106: 116000 | N106: 39000 | O106: No | P106: David
A107: 100106 | B107: 46082 | C107: IB-01 | D107: Ibadan | E107: In-store | F107: Home | G107: Blender | H107: C1170 | I107: Returning | J107: 5 | K107: 42000 | L107: 0.05 | M107: 199500 | N107: 28000 | O107: No | P107: Kemi
A108: 100107 | B108: 46049 | C108: PH-01 | D108: Port Harcourt | E108: In-store | F108: Home | G108: Standing Fan | H108: C1082 | I108: Returning | J108: 1 | K108: 58000 | L108: 0.1 | M108: 52200 | N108: 39000 | O108: No | P108: Aisha
...

Sheet in
A1: Transaction_ID | B1: Date | C1: Store_ID | D1: State | E1: Channel | F1: Product_Category | G1: Product | H1: Customer_ID | I1: Customer_Type | J1: Units | K1: Unit_Price_NGN | L1: Discount_Pct | M1: Revenue_Reported_NGN | N1: Cost_Per_Unit_NGN | O1: Return_Flag | P1: Sales_Rep | Q1: Q | S1: S | T1: T | U1: u | V1: V | W1: w
A2: 100001 | B2: 46167 | C2: AB-02 | D2: Abuja | E2: WhatsApp | F2: Home | G2: Standing Fan | H2: C1141 | I2: New | J2: 1 | K2: 58000 | L2: 0 | M2: 58000 | O2: No | P2: Chinedu | Q2: {=IF(N2="",_xlfn.XLOOKUP(1,($G$2:$G$433=G2)*($N$2:$N$433<>""),$N$2:$N$433),"")} -> 39000 | R2: =J2*K2*(1-L2) -> 58000 | S2: =IF(M2<>J2*K2*(1-L2),"Mismatch","Match") -> Match | V2: =M2-(J2*N2) -> 58000 | W2: =J2*K2*(1-L2) -> 58000 | X2: =W2-(J2*N2) -> 58000 | Y2: =M2-(J2*N2) -> 58000 | Z2: =SUM(Y2:Y433) -> 16617270 | AA2: =W2-(J2*N2) -> 58000
A3: 100002 | B3: 46129 | C3: LG-01 | D3: Lagos | E3: WhatsApp | F3: Electronics | G3: Smartphone | H3: C1083 | I3: Returning | J3: 5 | K3: 165000 | L3: 0.05 | M3: 627000 | N3: 112000 | O3: No | P3: Kemi | Q3: =COUNTIF($A$2:$A$433,A3)>1 -> FALSE | R3: =J3*K3*(1-L3) -> 783750 | S3: =IF(M3<>J3*K3*(1-L3),"Mismatch","Match") -> Mismatch | T3: =M3-(J3*K3*(1-L3)) -> -156750 | U3: =IF(AND(M3<>J3*K3*(1-L3),M3=J3*K3*(1-L3)*80%),"20% pattern","Other mismatch") -> 20% pattern | V3: =M3-(J3*N3) -> 67000 | W3: =J3*K3*(1-L3) -> 783750 | X3: =W3-(J3*N3) -> 223750 | Y3: =M3-(J3*N3) -> 67000 | AA3: =W2-(J2*N2) -> 58000
A4: 100003 | B4: 46079 | C4: AB-01 | D4: Abuja | E4: WhatsApp | F4: Electronics | G4: Earbuds | H4: C1029 | I4: Returning | J4: 3 | K4: 32000 | L4: 0.2 | M4: 76800 | N4: 19000 | O4: No | P4: Chinedu | Q4: =COUNTIF($A$2:$A$433,A4)>1 -> FALSE | R4: =J4*K4*(1-L4) -> 76800 | S4: =IF(M4<>J4*K4*(1-L4),"Mismatch","Match") -> Match | V4: =M4-(J4*N4) -> 19800 | W4: =J4*K4*(1-L4) -> 76800 | X4: =W4-(J4*N4) -> 19800 | Y4: =M4-(J4*N4) -> 19800 | Z4: =COUNTIF(F2:F433,"Accessory") -> 1
A5: 100004 | B5: 46182 | C5: KN-01 | D5: Kano | E5: Online | F5: Electronics | G5: Power Bank | H5: C1082 | I5: Returning | J5: 4 | K5: 26000 | L5: 0 | M5: 104000 | N5: 15000 | O5: No | P5: Grace | Q5: =COUNTIF($A$2:$A$433,A5)>1 -> FALSE | R5: =J5*K5*(1-L5) -> 104000 | S5: =IF(M5<>J5*K5*(1-L5),"Mismatch","Match") -> Match | V5: =M5-(J5*N5) -> 44000 | W5: =J5*K5*(1-L5) -> 104000 | X5: =W5-(J5*N5) -> 44000 | Y5: =M5-(J5*N5) -> 44000
A6: 100005 | B6: 46172 | C6: LG-01 | D6: Lagos | E6: Online | F6: Electronics | G6: Smartphone | H6: C1180 | I6: Returning | J6: 1 | K6: 165000 | L6: 0.05 | M6: 156750 | N6: 112000 | O6: No | P6: Chinedu | Q6: =COUNTIF($A$2:$A$433,A6)>1 -> FALSE | R6: =J6*K6*(1-L6) -> 156750 | S6: =IF(M6<>J6*K6*(1-L6),"Mismatch","Match") -> Match | V6: =M6-(J6*N6) -> 44750 | W6: =J6*K6*(1-L6) -> 156750 | X6: =W6-(J6*N6) -> 44750 | Y6: =M6-(J6*N6) -> 44750 | Z6: =COUNTIF(F2:F421,"Accessories") -> 106
A7: 100006 | B7: 46238 | C7: LG-02 | D7: Lagos | E7: In-store | F7: Accessories | G7: USB Cable | H7: C1161 | I7: Returning | J7: 3 | K7: 6500 | L7: 0.1 | M7: 17550 | N7: 2200 | O7: No | P7: Bola | Q7: =COUNTIF($A$2:$A$433,A7)>1 -> FALSE | S7: =IF(M7<>J7*K7*(1-L7),"Mismatch","Match") -> Match | V7: =M7-(J7*N7) -> 10950 | W7: =J7*K7*(1-L7) -> 17550 | X7: =W7-(J7*N7) -> 10950 | Y7: =M7-(J7*N7) -> 10950
A8: 100007 | B8: 46090 | C8: LG-01 | D8: Lagos | E8: In-store | F8: Electronics | G8: Power Bank | H8: C1007 | I8: New | J8: 3 | K8: 26000 | L8: 0.1 | M8: 70200 | N8: 15000 | O8: No | P8: Chinedu | Q8: =COUNTIF($A$2:$A$433,A8)>1 -> FALSE | S8: =IF(M8<>J8*K8*(1-L8),"Mismatch","Match") -> Match | V8: =M8-(J8*N8) -> 25200 | W8: =J8*K8*(1-L8) -> 70200 | X8: =W8-(J8*N8) -> 25200 | Y8: =M8-(J8*N8) -> 25200
A9: 100008 | B9: 46229 | C9: KN-01 | D9: Kano | E9: Online | F9: Electronics | G9: Smartphone | H9: C1051 | I9: Returning | J9: 5 | K9: 165000 | L9: 0.05 | M9: 783750 | N9: 112000 | O9: No | P9: Kemi | Q9: =COUNTIF($A$2:$A$433,A9)>1 -> FALSE | S9: =IF(M9<>J9*K9*(1-L9),"Mismatch","Match") -> Match | V9: =M9-(J9*N9) -> 223750 | W9: =J9*K9*(1-L9) -> 783750 | X9: =W9-(J9*N9) -> 223750 | Y9: =M9-(J9*N9) -> 223750
A10: 100009 | B10: 46028 | C10: IB-01 | D10: Ibadan | E10: In-store | F10: Home | G10: Blender | H10: C1111 | I10: Returning | J10: 3 | K10: 42000 | L10: 0.15 | M10: 107100 | N10: 28000 | O10: No | P10: Fatima | Q10: =COUNTIF($A$2:$A$433,A10)>1 -> FALSE | S10: =IF(M10<>J10*K10*(1-L10),"Mismatch","Match") -> Match | V10: =M10-(J10*N10) -> 23100 | W10: =J10*K10*(1-L10) -> 107100 | X10: =W10-(J10*N10) -> 23100 | Y10: =M10-(J10*N10) -> 23100
A11: 100010 | B11: 46248 | C11: PH-01 | D11: Port Harcourt | E11: In-store | F11: Electronics | G11: Smartphone | H11: C1153 | I11: Returning | J11: 1 | K11: 165000 | L11: 0 | M11: 165000 | N11: 112000 | O11: No | P11: David | Q11: =COUNTIF($A$2:$A$433,A11)>1 -> FALSE | S11: =IF(M11<>J11*K11*(1-L11),"Mismatch","Match") -> Match | V11: =M11-(J11*N11) -> 53000 | W11: =J11*K11*(1-L11) -> 165000 | X11: =W11-(J11*N11) -> 53000 | Y11: =M11-(J11*N11) -> 53000
A12: 100011 | B12: 46200 | C12: LG-01 | D12: Lagos | E12: In-store | F12: Electronics | G12: Earbuds | H12: C1059 | I12: Returning | J12: 1 | K12: 32000 | L12: 0 | M12: 32000 | N12: 19000 | O12: No | P12: David | Q12: =COUNTIF($A$2:$A$433,A12)>1 -> FALSE | S12: =IF(M12<>J12*K12*(1-L12),"Mismatch","Match") -> Match | V12: =M12-(J12*N12) -> 13000 | W12: =J12*K12*(1-L12) -> 32000 | X12: =W12-(J12*N12) -> 13000 | Y12: =M12-(J12*N12) -> 13000
A13: 100012 | B13: 46120 | C13: KN-01 | D13: Kano | E13: Online | F13: Accessories | G13: Phone Case | H13: C1028 | I13: New | J13: 1 | K13: 9000 | L13: 0 | M13: 9000 | N13: 3500 | O13: No | P13: David | Q13: =COUNTIF($A$2:$A$433,A13)>1 -> FALSE | S13: =IF(M13<>J13*K13*(1-L13),"Mismatch","Match") -> Match | V13: =M13-(J13*N13) -> 5500 | W13: =J13*K13*(1-L13) -> 9000 | X13: =W13-(J13*N13) -> 5500 | Y13: =M13-(J13*N13) -> 5500
A14: 100013 | B14: 46153 | C14: IB-01 | D14: Ibadan | E14: In-store | F14: Home | G14: Electric Kettle | H14: C1192 | I14: New | J14: 2 | K14: 24000 | L14: 0 | M14: 48000 | N14: 15000 | O14: No | P14: Ibrahim | Q14: =COUNTIF($A$2:$A$433,A14)>1 -> FALSE | S14: =IF(M14<>J14*K14*(1-L14),"Mismatch","Match") -> Match | V14: =M14-(J14*N14) -> 18000 | W14: =J14*K14*(1-L14) -> 48000 | X14: =W14-(J14*N14) -> 18000 | Y14: =M14-(J14*N14) -> 18000
A15: 100014 | B15: 46195 | C15: AB-02 | D15: Abuja | E15: WhatsApp | F15: Accessories | G15: Backpack | H15: C1022 | I15: Returning | J15: 2 | K15: 28000 | L15: 0.25 | M15: 42000 | O15: No | P15: Fatima | Q15: {=IF(N15="",_xlfn.XLOOKUP(1,($G$2:$G$433=G15)*($N$2:$N$433<>""),$N$2:$N$433),"")} -> 16000 | S15: =IF(M15<>J15*K15*(1-L15),"Mismatch","Match") -> Match | V15: =M15-(J15*N15) -> 42000 | W15: =J15*K15*(1-L15) -> 42000 | X15: =W15-(J15*N15) -> 42000 | Y15: =M15-(J15*N15) -> 42000
A16: 100015 | B16: 46031 | C16: PH-01 | D16: Port Harcourt | E16: In-store | F16: Electronics | G16: Smartphone | H16: C1084 | I16: New | J16: 2 | K16: 165000 | L16: 0 | M16: 330000 | N16: 112000 | O16: No | P16: Grace | Q16: =COUNTIF($A$2:$A$433,A16)>1 -> FALSE | S16: =IF(M16<>J16*K16*(1-L16),"Mismatch","Match") -> Match | V16: =M16-(J16*N16) -> 106000 | W16: =J16*K16*(1-L16) -> 330000 | X16: =W16-(J16*N16) -> 106000 | Y16: =M16-(J16*N16) -> 106000
A17: 100016 | B17: 46228 | C17: LG-02 | D17: Lagos | E17: Online | F17: Accessories | G17: USB Cable | H17: C1123 | I17: New | J17: 1 | K17: 6500 | L17: 0.1 | M17: 4680 | N17: 2200 | O17: No | P17: Kemi | Q17: =COUNTIF($A$2:$A$433,A17)>1 -> FALSE | S17: =IF(M17<>J17*K17*(1-L17),"Mismatch","Match") -> Mismatch | T17: =M17-(J17*K17*(1-L17)) -> -1170 | U17: =IF(AND(M17<>J17*K17*(1-L17),M17=J17*K17*(1-L17)*80%),"20% pattern","Other mismatch") -> 20% pattern | V17: =M17-(J17*N17) -> 2480 | W17: =J17*K17*(1-L17) -> 5850 | X17: =W17-(J17*N17) -> 3650 | Y17: =M17-(J17*N17) -> 2480
A18: 100017 | B18: 46032 | C18: KN-01 | D18: Kano | E18: WhatsApp | F18: Home | G18: Blender | H18: C1134 | I18: New | J18: 2 | K18: 42000 | L18: 0 | M18: 84000 | N18: 28000 | O18: No | P18: Ibrahim | Q18: =COUNTIF($A$2:$A$433,A18)>1 -> FALSE | S18: =IF(M18<>J18*K18*(1-L18),"Mismatch","Match") -> Match | V18: =M18-(J18*N18) -> 28000 | W18: =J18*K18*(1-L18) -> 84000 | X18: =W18-(J18*N18) -> 28000 | Y18: =M18-(J18*N18) -> 28000
A19: 100018 | B19: 46141 | C19: PH-01 | D19: Port Harcourt | E19: In-store | F19: Accessories | G19: USB Cable | H19: C1100 | I19: Returning | J19: 22 | K19: 6500 | L19: 0.15 | M19: 121550 | N19: 2200 | O19: No | P19: Kemi | Q19: =COUNTIF($A$2:$A$433,A19)>1 -> FALSE | S19: =IF(M19<>J19*K19*(1-L19),"Mismatch","Match") -> Match | V19: =M19-(J19*N19) -> 73150 | W19: =J19*K19*(1-L19) -> 121550 | X19: =W19-(J19*N19) -> 73150 | Y19: =M19-(J19*N19) -> 73150
A20: 100019 | B20: 46148 | C20: LG-01 | D20: Lagos | E20: In-store | F20: Electronics | G20: Power Bank | H20: C1189 | I20: Returning | J20: 1 | K20: 26000 | L20: 0.15 | M20: 22100 | N20: 15000 | O20: No | P20: Bola | Q20: =COUNTIF($A$2:$A$433,A20)>1 -> FALSE | S20: =IF(M20<>J20*K20*(1-L20),"Mismatch","Match") -> Match | V20: =M20-(J20*N20) -> 7100 | W20: =J20*K20*(1-L20) -> 22100 | X20: =W20-(J20*N20) -> 7100 | Y20: =M20-(J20*N20) -> 7100
A21: 100020 | B21: 46131 | C21: AB-02 | D21: Abuja | E21: In-store | F21: Electronics | G21: Power Bank | H21: C1050 | I21: Returning | J21: 1 | K21: 26000 | L21: 0.25 | M21: 19500 | O21: No | P21: Ibrahim | Q21: {=IF(N21="",_xlfn.XLOOKUP(1,($G$2:$G$433=G21)*($N$2:$N$433<>""),$N$2:$N$433),"")} -> 15000 | R21: =SUBTOTAL(109,Q2:Q433) -> 921600 | S21: =IF(M21<>J21*K21*(1-L21),"Mismatch","Match") -> Match | V21: =M21-(J21*N21) -> 19500 | W21: =J21*K21*(1-L21) -> 19500 | X21: =W21-(J21*N21) -> 19500 | Y21: =M21-(J21*N21) -> 19500
A22: 100021 | B22: 46148 | C22: AB-02 | D22: Abuja | E22: WhatsApp | F22: Electronics | G22: Power Bank | H22: C1184 | I22: New | J22: 1 | K22: 26000 | L22: 0 | M22: 26000 | N22: 15000 | O22: No | P22: Kemi | Q22: =COUNTIF($A$2:$A$433,A22)>1 -> FALSE | S22: =IF(M22<>J22*K22*(1-L22),"Mismatch","Match") -> Match | V22: =M22-(J22*N22) -> 11000 | W22: =J22*K22*(1-L22) -> 26000 | X22: =W22-(J22*N22) -> 11000 | Y22: =M22-(J22*N22) -> 11000
A23: 100022 | B23: 46033 | C23: IB-01 | D23: Ibadan | E23: WhatsApp | F23: Accessories | G23: Backpack | H23: C1022 | I23: New | J23: 1 | K23: 28000 | L23: 0.05 | M23: 26600 | N23: 16000 | O23: No | P23: Bola | Q23: =COUNTIF($A$2:$A$433,A23)>1 -> FALSE | S23: =IF(M23<>J23*K23*(1-L23),"Mismatch","Match") -> Match | V23: =M23-(J23*N23) -> 10600 | W23: =J23*K23*(1-L23) -> 26600 | X23: =W23-(J23*N23) -> 10600 | Y23: =M23-(J23*N23) -> 10600
A24: 100023 | B24: 46052 | C24: AB-01 | D24: Abuja | E24: Online | F24: Electronics | G24: Earbuds | H24: C1004 | I24: Returning | J24: 1 | K24: 32000 | L24: 0.15 | M24: 27200 | N24: 19000 | O24: No | P24: David | Q24: =COUNTIF($A$2:$A$433,A24)>1 -> FALSE | S24: =IF(M24<>J24*K24*(1-L24),"Mismatch","Match") -> Match | V24: =M24-(J24*N24) -> 8200 | W24: =J24*K24*(1-L24) -> 27200 | X24: =W24-(J24*N24) -> 8200 | Y24: =M24-(J24*N24) -> 8200
A25: 100024 | B25: 46150 | C25: AB-01 | D25: Abuja | E25: In-store | F25: Home | G25: Standing Fan | H25: C1034 | I25: New | J25: 2 | K25: 58000 | L25: 0.2 | M25: 92800 | O25: Yes | P25: Grace | Q25: {=IF(N25="",_xlfn.XLOOKUP(1,($G$2:$G$433=G25)*($N$2:$N$433<>""),$N$2:$N$433),"")} -> 39000 | S25: =IF(M25<>J25*K25*(1-L25),"Mismatch","Match") -> Match | V25: =M25-(J25*N25) -> 92800 | W25: =J25*K25*(1-L25) -> 92800 | X25: =W25-(J25*N25) -> 92800 | Y25: =M25-(J25*N25) -> 92800
A26: 100025 | B26: 46027 | C26: KN-01 | D26: Kano | E26: In-store | F26: Home | G26: Standing Fan | H26: C1164 | I26: Returning | J26: 5 | K26: 58000 | L26: 0.05 | M26: 275500 | N26: 39000 | O26: No | P26: David | Q26: =COUNTIF($A$2:$A$433,A26)>1 -> FALSE | S26: =IF(M26<>J26*K26*(1-L26),"Mismatch","Match") -> Match | V26: =M26-(J26*N26) -> 80500 | W26: =J26*K26*(1-L26) -> 275500 | X26: =W26-(J26*N26) -> 80500 | Y26: =M26-(J26*N26) -> 80500
A27: 100026 | B27: 46203 | C27: IB-01 | D27: Ibadan | E27: In-store | F27: Accessories | G27: Phone Case | H27: C1155 | I27: Returning | J27: 2 | K27: 9000 | L27: 0.1 | M27: 16200 | O27: No | P27: Chinedu | Q27: {=IF(N27="",_xlfn.XLOOKUP(1,($G$2:$G$433=G27)*($N$2:$N$433<>""),$N$2:$N$433),"")} -> 3500 | S27: =IF(M27<>J27*K27*(1-L27),"Mismatch","Match") -> Match | V27: =M27-(J27*N27) -> 16200 | W27: =J27*K27*(1-L27) -> 16200 | X27: =W27-(J27*N27) -> 16200 | Y27: =M27-(J27*N27) -> 16200
A28: 100027 | B28: 46142 | C28: KN-01 | D28: Kano | E28: WhatsApp | F28: Home | G28: Standing Fan | H28: C1073 | I28: New | J28: 4 | K28: 58000 | L28: 0.05 | M28: 220400 | N28: 39000 | O28: No | P28: David | Q28: =COUNTIF($A$2:$A$433,A28)>1 -> FALSE | S28: =IF(M28<>J28*K28*(1-L28),"Mismatch","Match") -> Match | V28: =M28-(J28*N28) -> 64400 | W28: =J28*K28*(1-L28) -> 220400 | X28: =W28-(J28*N28) -> 64400 | Y28: =M28-(J28*N28) -> 64400
A29: 100028 | B29: 46156 | C29: AB-01 | D29: Abuja | E29: Online | F29: Electronics | G29: Power Bank | H29: C1136 | I29: Returning | J29: 22 | K29: 26000 | L29: 0.25 | M29: 429000 | N29: 15000 | O29: No | P29: Bola | Q29: =COUNTIF($A$2:$A$433,A29)>1 -> FALSE | S29: =IF(M29<>J29*K29*(1-L29),"Mismatch","Match") -> Match | V29: =M29-(J29*N29) -> 99000 | W29: =J29*K29*(1-L29) -> 429000 | X29: =W29-(J29*N29) -> 99000 | Y29: =M29-(J29*N29) -> 99000
A30: 100029 | B30: 46103 | C30: AB-01 | D30: Abuja | E30: In-store | F30: Home | G30: Standing Fan | H30: C1173 | I30: Returning | J30: 5 | K30: 58000 | L30: 0.1 | M30: 261000 | O30: No | P30: Chinedu | Q30: {=IF(N30="",_xlfn.XLOOKUP(1,($G$2:$G$433=G30)*($N$2:$N$433<>""),$N$2:$N$433),"")} -> 39000 | S30: =IF(M30<>J30*K30*(1-L30),"Mismatch","Match") -> Match | V30: =M30-(J30*N30) -> 261000 | W30: =J30*K30*(1-L30) -> 261000 | X30: =W30-(J30*N30) -> 261000 | Y30: =M30-(J30*N30) -> 261000
A31: 100030 | B31: 46209 | C31: KN-01 | D31: Kano | E31: Online | F31: Electronics | G31: Power Bank | H31: C1071 | I31: New | J31: 1 | K31: 26000 | L31: 0.05 | M31: 24700 | N31: 15000 | O31: No | P31: David | Q31: =COUNTIF($A$2:$A$433,A31)>1 -> FALSE | S31: =IF(M31<>J31*K31*(1-L31),"Mismatch","Match") -> Match | V31: =M31-(J31*N31) -> 9700 | W31: =J31*K31*(1-L31) -> 24700 | X31: =W31-(J31*N31) -> 9700 | Y31: =M31-(J31*N31) -> 9700
A32: 100031 | B32: 46182 | C32: AB-01 | D32: Abuja | E32: In-store | F32: Home | G32: Standing Fan | H32: C1047 | I32: New | J32: 2 | K32: 58000 | L32: 0.15 | M32: 98600 | N32: 39000 | O32: No | P32: Aisha | Q32: =COUNTIF($A$2:$A$433,A32)>1 -> FALSE | S32: =IF(M32<>J32*K32*(1-L32),"Mismatch","Match") -> Match | V32: =M32-(J32*N32) -> 20600 | W32: =J32*K32*(1-L32) -> 98600 | X32: =W32-(J32*N32) -> 20600 | Y32: =M32-(J32*N32) -> 20600
A33: 100032 | B33: 46109 | C33: PH-01 | D33: Port Harcourt | E33: Online | F33: Home | G33: Electric Kettle | H33: C1051 | I33: New | J33: 1 | K33: 24000 | L33: 0.05 | M33: 22800 | N33: 15000 | O33: No | P33: Kemi | Q33: =COUNTIF($A$2:$A$433,A33)>1 -> FALSE | S33: =IF(M33<>J33*K33*(1-L33),"Mismatch","Match") -> Match | V33: =M33-(J33*N33) -> 7800 | W33: =J33*K33*(1-L33) -> 22800 | X33: =W33-(J33*N33) -> 7800 | Y33: =M33-(J33*N33) -> 7800
A34: 100033 | B34: 46152 | C34: LG-01 | D34: Lagos | E34: In-store | F34: Home | G34: Standing Fan | H34: C1094 | I34: New | J34: 3 | K34: 58000 | L34: 0 | M34: 174000 | N34: 39000 | O34: No | P34: Aisha | Q34: =COUNTIF($A$2:$A$433,A34)>1 -> FALSE | S34: =IF(M34<>J34*K34*(1-L34),"Mismatch","Match") -> Match | V34: =M34-(J34*N34) -> 57000 | W34: =J34*K34*(1-L34) -> 174000 | X34: =W34-(J34*N34) -> 57000 | Y34: =M34-(J34*N34) -> 57000
A35: 100034 | B35: 46157 | C35: PH-01 | D35: Port Harcourt | E35: In-store | F35: Home | G35: Standing Fan | H35: C1089 | I35: Returning | J35: 1 | K35: 58000 | L35: 0.15 | M35: 49300 | N35: 39000 | O35: No | P35: Bola | Q35: =COUNTIF($A$2:$A$433,A35)>1 -> FALSE | S35: =IF(M35<>J35*K35*(1-L35),"Mismatch","Match") -> Match | V35: =M35-(J35*N35) -> 10300 | W35: =J35*K35*(1-L35) -> 49300 | X35: =W35-(J35*N35) -> 10300 | Y35: =M35-(J35*N35) -> 10300
A36: 100035 | B36: 46076 | C36: KN-01 | D36: Kano | E36: In-store | F36: Accessories | G36: Backpack | H36: C1048 | I36: Returning | J36: 25 | K36: 28000 | L36: 0.05 | M36: 665000 | N36: 16000 | O36: No | P36: Ibrahim | Q36: =COUNTIF($A$2:$A$433,A36)>1 -> FALSE | S36: =IF(M36<>J36*K36*(1-L36),"Mismatch","Match") -> Match | V36: =M36-(J36*N36) -> 265000 | W36: =J36*K36*(1-L36) -> 665000 | X36: =W36-(J36*N36) -> 265000 | Y36: =M36-(J36*N36) -> 265000
A37: 100036 | B37: 46076 | C37: KN-01 | D37: Kano | E37: In-store | F37: Electronics | G37: Earbuds | H37: C1056 | I37: New | J37: 2 | K37: 32000 | L37: 0.05 | M37: 60800 | N37: 19000 | O37: Yes | P37: Bola | Q37: =COUNTIF($A$2:$A$433,A37)>1 -> FALSE | S37: =IF(M37<>J37*K37*(1-L37),"Mismatch","Match") -> Match | V37: =M37-(J37*N37) -> 22800 | W37: =J37*K37*(1-L37) -> 60800 | X37: =W37-(J37*N37) -> 22800 | Y37: =M37-(J37*N37) -> 22800
A38: 100037 | B38: 46124 | C38: AB-01 | D38: Abuja | E38: In-store | F38: Accessories | G38: Backpack | H38: C1036 | I38: New | J38: 2 | K38: 28000 | L38: 0 | M38: 56000 | N38: 16000 | O38: No | P38: Grace | Q38: =COUNTIF($A$2:$A$433,A38)>1 -> FALSE | S38: =IF(M38<>J38*K38*(1-L38),"Mismatch","Match") -> Match | V38: =M38-(J38*N38) -> 24000 | W38: =J38*K38*(1-L38) -> 56000 | X38: =W38-(J38*N38) -> 24000 | Y38: =M38-(J38*N38) -> 24000
A39: 100038 | B39: 46037 | C39: KN-01 | D39: Kano | E39: Online | F39: Electronics | G39: Earbuds | H39: C1138 | I39: Returning | J39: 2 | K39: 32000 | L39: 0 | M39: 64000 | N39: 19000 | O39: No | P39: Aisha | Q39: =COUNTIF($A$2:$A$433,A39)>1 -> FALSE | S39: =IF(M39<>J39*K39*(1-L39),"Mismatch","Match") -> Match | V39: =M39-(J39*N39) -> 26000 | W39: =J39*K39*(1-L39) -> 64000 | X39: =W39-(J39*N39) -> 26000 | Y39: =M39-(J39*N39) -> 26000
A40: 100039 | B40: 46116 | C40: AB-02 | D40: Abuja | E40: Online | F40: Accessories | G40: USB Cable | H40: C1044 | I40: New | J40: 3 | K40: 6500 | L40: 0.1 | M40: 17550 | N40: 2200 | O40: No | P40: Grace | Q40: =COUNTIF($A$2:$A$433,A40)>1 -> FALSE | S40: =IF(M40<>J40*K40*(1-L40),"Mismatch","Match") -> Match | V40: =M40-(J40*N40) -> 10950 | W40: =J40*K40*(1-L40) -> 17550 | X40: =W40-(J40*N40) -> 10950 | Y40: =M40-(J40*N40) -> 10950
A41: 100040 | B41: 46145 | C41: AB-01 | D41: Abuja | E41: WhatsApp | F41: Home | G41: Standing Fan | H41: C1063 | I41: Returning | J41: 1 | K41: 58000 | L41: 0.05 | M41: 55100 | N41: 39000 | O41: No | P41: Kemi | Q41: =COUNTIF($A$2:$A$433,A41)>1 -> FALSE | S41: =IF(M41<>J41*K41*(1-L41),"Mismatch","Match") -> Match | V41: =M41-(J41*N41) -> 16100 | W41: =J41*K41*(1-L41) -> 55100 | X41: =W41-(J41*N41) -> 16100 | Y41: =M41-(J41*N41) -> 16100
A42: 100041 | B42: 46035 | C42: PH-01 | D42: Port Harcourt | E42: WhatsApp | F42: Electronics | G42: Earbuds | H42: C1001 | I42: Returning | J42: 3 | K42: 32000 | L42: 0.1 | M42: 86400 | N42: 19000 | O42: No | P42: Bola | Q42: =COUNTIF($A$2:$A$433,A42)>1 -> FALSE | S42: =IF(M42<>J42*K42*(1-L42),"Mismatch","Match") -> Match | V42: =M42-(J42*N42) -> 29400 | W42: =J42*K42*(1-L42) -> 86400 | X42: =W42-(J42*N42) -> 29400 | Y42: =M42-(J42*N42) -> 29400
... A51: 100050 | B51: 46056 | C51: KN-01 | D51: Kano | E51: In-store | F51: Accessories | G51: Phone Case | H51: C1080 | I51: Returning | J51: 3 | K51: 9000 | L51: 0 | M51: 27000 | N51: 3500 | O51: No | P51: Chinedu | Q51: =COUNTIF($A$2:$A$433,A51)>1 -> FALSE | S51: =IF(M51<>J51*K51*(1-L51),"Mismatch","Match") -> Match | V51: =M51-(J51*N51) -> 16500 | W51: =J51*K51*(1-L51) -> 27000 | X51: =W51-(J51*N51) -> 16500 | Y51: =M51-(J51*N51) -> 16500
A52: 100051 | B52: 46035 | C52: AB-02 | D52: Abuja | E52: Online | F52: Home | G52: Blender | H52: C1111 | I52: New | J52: 2 | K52: 42000 | L52: 0.1 | M52: 75600 | O52: No | P52: Chinedu | Q52: {=IF(N52="",_xlfn.XLOOKUP(1,($G$2:$G$433=G52)*($N$2:$N$433<>""),$N$2:$N$433),"")} -> 28000 | S52: =IF(M52<>J52*K52*(1-L52),"Mismatch","Match") -> Match | V52: =M52-(J52*N52) -> 75600 | W52: =J52*K52*(1-L52) -> 75600 | X52: =W52-(J52*N52) -> 75600 | Y52: =M52-(J52*N52) -> 75600
A53: 100052 | B53: 46033 | C53: PH-01 | D53: Port Harcourt | E53: WhatsApp | F53: Electronics | G53: Smartphone | H53: C1005 | I53: Returning | J53: 4 | K53: 165000 | L53: 0 | M53: 660000 | N53: 112000 | O53: No | P53: Chinedu | Q53: =COUNTIF($A$2:$A$433,A53)>1 -> FALSE | S53: =IF(M53<>J53*K53*(1-L53),"Mismatch","Match") -> Match | V53: =M53-(J53*N53) -> 212000 | W53: =J53*K53*(1-L53) -> 660000 | X53: =W53-(J53*N53) -> 212000 | Y53: =M53-(J53*N53) -> 212000
A54: 100053 | B54: 46180 | C54: KN-01 | D54: Kano | E54: In-store | F54: Accessories | G54: USB Cable | H54: C1193 | I54: Returning | J54: 4 | K54: 6500 | L54: 0 | M54: 26000 | N54: 2200 | O54: No | P54: Ibrahim | Q54: =COUNTIF($A$2:$A$433,A54)>1 -> FALSE | S54: =IF(M54<>J54*K54*(1-L54),"Mismatch","Match") -> Match | V54: =M54-(J54*N54) -> 17200 | W54: =J54*K54*(1-L54) -> 26000 | X54: =W54-(J54*N54) -> 17200 | Y54: =M54-(J54*N54) -> 17200
A55: 100054 | B55: 46140 | C55: AB-01 | D55: Abuja | E55: In-store | F55: Accessories | G55: Phone Case | H55: C1030 | I55: Returning | J55: 1 | K55: 9000 | L55: 0.1 | M55: 8100 | N55: 3500 | O55: No | P55: Aisha | Q55: =COUNTIF($A$2:$A$433,A55)>1 -> FALSE | S55: =IF(M55<>J55*K55*(1-L55),"Mismatch","Match") -> Match | V55: =M55-(J55*N55) -> 4600 | W55: =J55*K55*(1-L55) -> 8100 | X55: =W55-(J55*N55) -> 4600 | Y55: =M55-(J55*N55) -> 4600
A56: 100055 | B56: 46178 | C56: KN-01 | D56: Kano | E56: In-store | F56: Electronics | G56: Power Bank | H56: C1019 | I56: New | J56: 2 | K56: 26000 | L56: 0.15 | M56: 44200 | N56: 15000 | O56: No | P56: Bola | Q56: =COUNTIF($A$2:$A$433,A56)>1 -> FALSE | S56: =IF(M56<>J56*K56*(1-L56),"Mismatch","Match") -> Match | V56: =M56-(J56*N56) -> 14200 | W56: =J56*K56*(1-L56) -> 44200 | X56: =W56-(J56*N56) -> 14200 | Y56: =M56-(J56*N56) -> 14200
A57: 100056 | B57: 46191 | C57: KN-01 | D57: Kano | E57: In-store | F57: Accessories | G57: Phone Case | H57: C1187 | I57: New | J57: 1 | K57: 9000 | L57: 0.05 | M57: 6840 | N57: 3500 | O57: No | P57: Bola | Q57: =COUNTIF($A$2:$A$433,A57)>1 -> FALSE | S57: =IF(M57<>J57*K57*(1-L57),"Mismatch","Match") -> Mismatch | T57: =M57-(J57*K57*(1-L57)) -> -1710 | U57: =IF(AND(M57<>J57*K57*(1-L57),M57=J57*K57*(1-L57)*80%),"20% pattern","Other mismatch") -> 20% pattern | V57: =M57-(J57*N57) -> 3340 | W57: =J57*K57*(1-L57) -> 8550 | X57: =W57-(J57*N57) -> 5050 | Y57: =M57-(J57*N57) -> 3340
A58: 100057 | B58: 46196 | C58: IB-01 | D58: Ibadan | E58: Online | F58: Electronics | G58: Power Bank | H58: C1190 | I58: New | J58: 1 | K58: 26000 | L58: 0.15 | M58: 22100 | N58: 15000 | O58: No | P58: Fatima | Q58: =COUNTIF($A$2:$A$433,A58)>1 -> FALSE | S58: =IF(M58<>J58*K58*(1-L58),"Mismatch","Match") -> Match | V58: =M58-(J58*N58) -> 7100 | W58: =J58*K58*(1-L58) -> 22100 | X58: =W58-(J58*N58) -> 7100 | Y58: =M58-(J58*N58) -> 7100
A59: 100058 | B59: 46140 | C59: KN-01 | D59: Kano | E59: In-store | F59: Accessories | G59: Backpack | H59: C1069 | I59: Returning | J59: 2 | K59: 28000 | L59: 0 | M59: 56000 | N59: 16000 | O59: No | P59: Aisha | Q59: =COUNTIF($A$2:$A$433,A59)>1 -> FALSE | S59: =IF(M59<>J59*K59*(1-L59),"Mismatch","Match") -> Match | V59: =M59-(J59*N59) -> 24000 | W59: =J59*K59*(1-L59) -> 56000 | X59: =W59-(J59*N59) -> 24000 | Y59: =M59-(J59*N59) -> 24000
A60: 100059 | B60: 46039 | C60: LG-02 | D60: Lagos | E60: Online | F60: Home | G60: Blender | H60: C1074 | I60: Returning | J60: 2 | K60: 42000 | L60: 0.1 | M60: 75600 | N60: 28000 | O60: No | P60: Aisha | Q60: =COUNTIF($A$2:$A$433,A60)>1 -> FALSE | S60: =IF(M60<>J60*K60*(1-L60),"Mismatch","Match") -> Match | V60: =M60-(J60*N60) -> 19600 | W60: =J60*K60*(1-L60) -> 75600 | X60: =W60-(J60*N60) -> 19600 | Y60: =M60-(J60*N60) -> 19600
A61: 100060 | B61: 46046 | C61: IB-01 | D61: Ibadan | E61: Online | F61: Electronics | G61: Earbuds | H61: C1156 | I61: Returning | J61: 1 | K61: 32000 | L61: 0.1 | M61: 28800 | N61: 19000 | O61: No | P61: Bola | Q61: =COUNTIF($A$2:$A$433,A61)>1 -> FALSE | S61: =IF(M61<>J61*K61*(1-L61),"Mismatch","Match") -> Match | V61: =M61-(J61*N61) -> 9800 | W61: =J61*K61*(1-L61) -> 28800 | X61: =W61-(J61*N61) -> 9800 | Y61: =M61-(J61*N61) -> 9800
A62: 100061 | B62: 46251 | C62: LG-02 | D62: Lagos | E62: In-store | F62: Electronics | G62: Earbuds | H62: C1039 | I62: Returning | J62: 1 | K62: 32000 | L62: 0.15 | M62: 27200 | N62: 19000 | O62: No | P62: Aisha | Q62: =COUNTIF($A$2:$A$433,A62)>1 -> TRUE | S62: =IF(M62<>J62*K62*(1-L62),"Mismatch","Match") -> Match | V62: =M62-(J62*N62) -> 8200 | W62: =J62*K62*(1-L62) -> 27200 | X62: =W62-(J62*N62) -> 8200 | Y62: =M62-(J62*N62) -> 8200
A63: 100062 | B63: 46161 | C63: PH-01 | D63: Port Harcourt | E63: Online | F63: Electronics | G63: Smartphone | H63: C1045 | I63: New | J63: 3 | K63: 165000 | L63: 0 | M63: 495000 | N63: 112000 | O63: No | P63: Aisha | Q63: =COUNTIF($A$2:$A$433,A63)>1 -> FALSE | S63: =IF(M63<>J63*K63*(1-L63),"Mismatch","Match") -> Match | V63: =M63-(J63*N63) -> 159000 | W63: =J63*K63*(1-L63) -> 495000 | X63: =W63-(J63*N63) -> 159000 | Y63: =M63-(J63*N63) -> 159000
A64: 100063 | B64: 46114 | C64: LG-02 | D64: Lagos | E64: In-store | F64: Home | G64: Standing Fan | H64: C1164 | I64: New | J64: 1 | K64: 58000 | L64: 0 | M64: 58000 | N64: 39000 | O64: No | P64: Fatima | Q64: =COUNTIF($A$2:$A$433,A64)>1 -> FALSE | S64: =IF(M64<>J64*K64*(1-L64),"Mismatch","Match") -> Match | V64: =M64-(J64*N64) -> 19000 | W64: =J64*K64*(1-L64) -> 58000 | X64: =W64-(J64*N64) -> 19000 | Y64: =M64-(J64*N64) -> 19000
A65: 100064 | B65: 46224 | C65: LG-01 | D65: Lagos | E65: WhatsApp | F65: Home | G65: Electric Kettle | H65: C1179 | I65: New | J65: 1 | K65: 24000 | L65: 0.05 | M65: 22800 | N65: 15000 | O65: No | P65: Kemi | Q65: =COUNTIF($A$2:$A$433,A65)>1 -> FALSE | S65: =IF(M65<>J65*K65*(1-L65),"Mismatch","Match") -> Match | V65: =M65-(J65*N65) -> 7800 | W65: =J65*K65*(1-L65) -> 22800 | X65: =W65-(J65*N65) -> 7800 | Y65: =M65-(J65*N65) -> 7800
A66: 100065 | B66: 46172 | C66: PH-01 | D66: Port Harcourt | E66: In-store | F66: Electronics | G66: Smartphone | H66: C1055 | I66: Returning | J66: 4 | K66: 165000 | L66: 0.1 | M66: 594000 | N66: 112000 | O66: No | P66: David | Q66: =COUNTIF($A$2:$A$433,A66)>1 -> FALSE | S66: =IF(M66<>J66*K66*(1-L66),"Mismatch","Match") -> Match | V66: =M66-(J66*N66) -> 146000 | W66: =J66*K66*(1-L66) -> 594000 | X66: =W66-(J66*N66) -> 146000 | Y66: =M66-(J66*N66) -> 146000
A67: 100066 | B67: 46107 | C67: IB-01 | D67: Ibadan | E67: Online | F67: Home | G67: Blender | H67: C1106 | I67: Returning | J67: 3 | K67: 42000 | L67: 0.1 | M67: 113400 | N67: 28000 | O67: No | P67: Kemi | Q67: =COUNTIF($A$2:$A$433,A67)>1 -> FALSE | S67: =IF(M67<>J67*K67*(1-L67),"Mismatch","Match") -> Match | V67: =M67-(J67*N67) -> 29400 | W67: =J67*K67*(1-L67) -> 113400 | X67: =W67-(J67*N67) -> 29400 | Y67: =M67-(J67*N67) -> 29400
A68: 100067 | B68: 46210 | C68: AB-02 | D68: Abuja | E68: WhatsApp | F68: Accessories | G68: Backpack | H68: C1157 | I68: New | J68: 3 | K68: 28000 | L68: 0.15 | M68: 57120 | N68: 16000 | O68: No | P68: David | Q68: =COUNTIF($A$2:$A$433,A68)>1 -> FALSE | S68: =IF(M68<>J68*K68*(1-L68),"Mismatch","Match") -> Mismatch | T68: =M68-(J68*K68*(1-L68)) -> -14280 | U68: =IF(AND(M68<>J68*K68*(1-L68),M68=J68*K68*(1-L68)*80%),"20% pattern","Other mismatch") -> 20% pattern | V68: =M68-(J68*N68) -> 9120 | W68: =J68*K68*(1-L68) -> 71400 | X68: =W68-(J68*N68) -> 23400 | Y68: =M68-(J68*N68) -> 9120
A69: 100068 | B69: 46111 | C69: AB-02 | D69: Abuja | E69: Online | F69: Accessories | G69: Backpack | H69: C1000 | I69: New | J69: 4 | K69: 28000 | L69: 0.05 | M69: 106400 | N69: 16000 | O69: No | P69: David | Q69: =COUNTIF($A$2:$A$433,A69)>1 -> FALSE | S69: =IF(M69<>J69*K69*(1-L69),"Mismatch","Match") -> Match | V69: =M69-(J69*N69) -> 42400 | W69: =J69*K69*(1-L69) -> 106400 | X69: =W69-(J69*N69) -> 42400 | Y69: =M69-(J69*N69) -> 42400
A70: 100069 | B70: 46092 | C70: PH-01 | D70: Port Harcourt | E70: In-store | F70: Electronics | G70: Smartphone | H70: C1032 | I70: New | J70: 3 | K70: 165000 | L70: 0.05 | M70: 470250 | N70: 112000 | O70: No | P70: Bola | Q70: =COUNTIF($A$2:$A$433,A70)>1 -> FALSE | S70: =IF(M70<>J70*K70*(1-L70),"Mismatch","Match") -> Match | V70: =M70-(J70*N70) -> 134250 | W70: =J70*K70*(1-L70) -> 470250 | X70: =W70-(J70*N70) -> 134250 | Y70: =M70-(J70*N70) -> 134250
A71: 100070 | B71: 46147 | C71: PH-01 | D71: Port Harcourt | E71: In-store | F71: Home | G71: Standing Fan | H71: C1024 | I71: New | J71: 3 | K71: 58000 | L71: 0 | M71: 174000 | O71: No | P71: Ibrahim | Q71: {=IF(N71="",_xlfn.XLOOKUP(1,($G$2:$G$433=G71)*($N$2:$N$433<>""),$N$2:$N$433),"")} -> 39000 | S71: =IF(M71<>J71*K71*(1-L71),"Mismatch","Match") -> Match | V71: =M71-(J71*N71) -> 174000 | W71: =J71*K71*(1-L71) -> 174000 | X71: =W71-(J71*N71) -> 174000 | Y71: =M71-(J71*N71) -> 174000
A72: 100071 | B72: 46028 | C72: LG-02 | D72: Lagos | E72: Online | F72: Electronics | G72: Power Bank | H72: C1018 | I72: Returning | J72: 4 | K72: 26000 | L72: 0.1 | M72: 93600 | N72: 15000 | O72: No | P72: Chinedu | Q72: =COUNTIF($A$2:$A$433,A72)>1 -> FALSE | S72: =IF(M72<>J72*K72*(1-L72),"Mismatch","Match") -> Match | V72: =M72-(J72*N72) -> 33600 | W72: =J72*K72*(1-L72) -> 93600 | X72: =W72-(J72*N72) -> 33600 | Y72: =M72-(J72*N72) -> 33600
A73: 100072 | B73: 46182 | C73: IB-01 | D73: Ibadan | E73: In-store | F73: Home | G73: Standing Fan | H73: C1058 | I73: New | J73: 3 | K73: 58000 | L73: 0.1 | M73: 125280 | N73: 39000 | O73: No | P73: Grace | Q73: =COUNTIF($A$2:$A$433,A73)>1 -> FALSE | S73: =IF(M73<>J73*K73*(1-L73),"Mismatch","Match") -> Mismatch | T73: =M73-(J73*K73*(1-L73)) -> -31320 | U73: =IF(AND(M73<>J73*K73*(1-L73),M73=J73*K73*(1-L73)*80%),"20% pattern","Other mismatch") -> 20% pattern | V73: =M73-(J73*N73) -> 8280 | W73: =J73*K73*(1-L73) -> 156600 | X73: =W73-(J73*N73) -> 39600 | Y73: =M73-(J73*N73) -> 8280
A74: 100073 | B74: 46086 | C74: AB-01 | D74: Abuja | E74: Online | F74: Electronics | G74: Power Bank | H74: C1086 | I74: Returning | J74: 1 | K74: 26000 | L74: 0.1 | M74: 23400 | N74: 15000 | O74: Yes | P74: Bola | Q74: =COUNTIF($A$2:$A$433,A74)>1 -> FALSE | S74: =IF(M74<>J74*K74*(1-L74),"Mismatch","Match") -> Match | V74: =M74-(J74*N74) -> 8400 | W74: =J74*K74*(1-L74) -> 23400 | X74: =W74-(J74*N74) -> 8400 | Y74: =M74-(J74*N74) -> 8400
A75: 100074 | B75: 46132 | C75: IB-01 | D75: Ibadan | E75: In-store | F75: Accessories | G75: USB Cable | H75: C1043 | I75: New | J75: 4 | K75: 6500 | L75: 0.05 | M75: 24700 | N75: 2200 | O75: No | P75: Chinedu | Q75: =COUNTIF($A$2:$A$433,A75)>1 -> TRUE | S75: =IF(M75<>J75*K75*(1-L75),"Mismatch","Match") -> Match | V75: =M75-(J75*N75) -> 15900 | W75: =J75*K75*(1-L75) -> 24700 | X75: =W75-(J75*N75) -> 15900 | Y75: =M75-(J75*N75) -> 15900
A76: 100075 | B76: 46256 | C76: LG-01 | D76: Lagos | E76: In-store | F76: Electronics | G76: Smartphone | H76: C1188 | I76: Returning | J76: 1 | K76: 165000 | L76: 0.05 | M76: 156750 | N76: 112000 | O76: No | P76: Fatima | Q76: =COUNTIF($A$2:$A$433,A76)>1 -> FALSE | S76: =IF(M76<>J76*K76*(1-L76),"Mismatch","Match") -> Match | V76: =M76-(J76*N76) -> 44750 | W76: =J76*K76*(1-L76) -> 156750 | X76: =W76-(J76*N76) -> 44750 | Y76: =M76-(J76*N76) -> 44750
A77: 100076 | B77: 46064 | C77: LG-01 | D77: Lagos | E77: In-store | F77: Electronics | G77: Power Bank | H77: C1104 | I77: New | J77: 4 | K77: 26000 | L77: 0 | M77: 104000 | N77: 15000 | O77: No | P77: Aisha | Q77: =COUNTIF($A$2:$A$433,A77)>1 -> FALSE | S77: =IF(M77<>J77*K77*(1-L77),"Mismatch","Match") -> Match | V77: =M77-(J77*N77) -> 44000 | W77: =J77*K77*(1-L77) -> 104000 | X77: =W77-(J77*N77) -> 44000 | Y77: =M77-(J77*N77) -> 44000
A78: 100077 | B78: 46156 | C78: LG-02 | D78: Lagos | E78: In-store | F78: Accessories | G78: Phone Case | H78: C1192 | I78: New | J78: 2 | K78: 9000 | L78: 0.15 | M78: 15300 | N78: 3500 | O78: No | P78: Chinedu | Q78: =COUNTIF($A$2:$A$433,A78)>1 -> FALSE | S78: =IF(M78<>J78*K78*(1-L78),"Mismatch","Match") -> Match | V78: =M78-(J78*N78) -> 8300 | W78: =J78*K78*(1-L78) -> 15300 | X78: =W78-(J78*N78) -> 8300 | Y78: =M78-(J78*N78) -> 8300
A79: 100078 | B79: 46209 | C79: LG-01 | D79: Lagos | E79: In-store | F79: Accessories | G79: USB Cable | H79: C1108 | I79: Returning | J79: 2 | K79: 6500 | L79: 0.1 | M79: 11700 | N79: 2200 | O79: No | P79: Kemi | Q79: =COUNTIF($A$2:$A$433,A79)>1 -> FALSE | S79: =IF(M79<>J79*K79*(1-L79),"Mismatch","Match") -> Match | V79: =M79-(J79*N79) -> 7300 | W79: =J79*K79*(1-L79) -> 11700 | X79: =W79-(J79*N79) -> 7300 | Y79: =M79-(J79*N79) -> 7300
A80: 100079 | B80: 46058 | C80: LG-02 | D80: Lagos | E80: In-store | F80: Home | G80: Standing Fan | H80: C1159 | I80: Returning | J80: 2 | K80: 58000 | L80: 0.1 | M80: 104400 | N80: 39000 | O80: No | P80: Aisha | Q80: =COUNTIF($A$2:$A$433,A80)>1 -> FALSE | S80: =IF(M80<>J80*K80*(1-L80),"Mismatch","Match") -> Match | V80: =M80-(J80*N80) -> 26400 | W80: =J80*K80*(1-L80) -> 104400 | X80: =W80-(J80*N80) -> 26400 | Y80: =M80-(J80*N80) -> 26400
A81: 100080 | B81: 46255 | C81: IB-01 | D81: Ibadan | E81: Online | F81: Accessories | G81: Backpack | H81: C1017 | I81: Returning | J81: 2 | K81: 28000 | L81: 0.1 | M81: 50400 | N81: 16000 | O81: No | P81: Kemi | Q81: =COUNTIF($A$2:$A$433,A81)>1 -> FALSE | S81: =IF(M81<>J81*K81*(1-L81),"Mismatch","Match") -> Match | V81: =M81-(J81*N81) -> 18400 | W81: =J81*K81*(1-L81) -> 50400 | X81: =W81-(J81*N81) -> 18400 | Y81: =M81-(J81*N81) -> 18400
A82: 100081 | B82: 46151 | C82: LG-02 | D82: Lagos | E82: Online | F82: Electronics | G82: Earbuds | H82: C1143 | I82: New | J82: 2 | K82: 32000 | L82: 0 | M82: 64000 | N82: 19000 | O82: No | P82: Aisha | Q82: =COUNTIF($A$2:$A$433,A82)>1 -> FALSE | S82: =IF(M82<>J82*K82*(1-L82),"Mismatch","Match") -> Match | V82: =M82-(J82*N82) -> 26000 | W82: =J82*K82*(1-L82) -> 64000 | X82: =W82-(J82*N82) -> 26000 | Y82: =M82-(J82*N82) -> 26000
A83: 100082 | B83: 46149 | C83: AB-01 | D83: Abuja | E83: Online | F83: Electronics | G83: Smartphone | H83: C1089 | I83: New | J83: 2 | K83: 165000 | L83: 0.1 | M83: 297000 | O83: No | P83: Fatima | Q83: {=IF(N83="",_xlfn.XLOOKUP(1,($G$2:$G$433=G83)*($N$2:$N$433<>""),$N$2:$N$433),"")} -> 112000 | S83: =IF(M83<>J83*K83*(1-L83),"Mismatch","Match") -> Match | V83: =M83-(J83*N83) -> 297000 | W83: =J83*K83*(1-L83) -> 297000 | X83: =W83-(J83*N83) -> 297000 | Y83: =M83-(J83*N83) -> 297000
A84: 100083 | B84: 46079 | C84: LG-02 | D84: Lagos | E84: In-store | F84: Electronics | G84: Smartphone | H84: C1133 | I84: Returning | J84: 3 | K84: 165000 | L84: 0.1 | M84: 445500 | N84: 112000 | O84: Yes | P84: Fatima | Q84: =COUNTIF($A$2:$A$433,A84)>1 -> FALSE | S84: =IF(M84<>J84*K84*(1-L84),"Mismatch","Match") -> Match | V84: =M84-(J84*N84) -> 109500 | W84: =J84*K84*(1-L84) -> 445500 | X84: =W84-(J84*N84) -> 109500 | Y84: =M84-(J84*N84) -> 109500
A85: 100084 | B85: 46226 | C85: AB-01 | D85: Abuja | E85: In-store | F85: Electronics | G85: Power Bank | H85: C1097 | I85: New | J85: 4 | K85: 26000 | L85: 0 | M85: 104000 | N85: 15000 | O85: Yes | P85: Kemi | Q85: =COUNTIF($A$2:$A$433,A85)>1 -> FALSE | S85: =IF(M85<>J85*K85*(1-L85),"Mismatch","Match") -> Match | V85: =M85-(J85*N85) -> 44000 | W85: =J85*K85*(1-L85) -> 104000 | X85: =W85-(J85*N85) -> 44000 | Y85: =M85-(J85*N85) -> 44000
A86: 100085 | B86: 46227 | C86: PH-01 | D86: Port Harcourt | E86: WhatsApp | F86: Electronics | G86: Power Bank | H86: C1020 | I86: Returning | J86: 3 | K86: 26000 | L86: 0 | M86: 78000 | N86: 15000 | O86: No | P86: Aisha | Q86: =COUNTIF($A$2:$A$433,A86)>1 -> FALSE | S86: =IF(M86<>J86*K86*(1-L86),"Mismatch","Match") -> Match | V86: =M86-(J86*N86) -> 33000 | W86: =J86*K86*(1-L86) -> 78000 | X86: =W86-(J86*N86) -> 33000 | Y86: =M86-(J86*N86) -> 33000
A87: 100086 | B87: 46068 | C87: KN-01 | D87: Kano | E87: Online | F87: Electronics | G87: Earbuds | H87: C1177 | I87: Returning | J87: 4 | K87: 32000 | L87: 0.1 | M87: 115200 | N87: 19000 | O87: No | P87: Fatima | Q87: =COUNTIF($A$2:$A$433,A87)>1 -> FALSE | S87: =IF(M87<>J87*K87*(1-L87),"Mismatch","Match") -> Match | V87: =M87-(J87*N87) -> 39200 | W87: =J87*K87*(1-L87) -> 115200 | X87: =W87-(J87*N87) -> 39200 | Y87: =M87-(J87*N87) -> 39200
A88: 100087 | B88: 46032 | C88: AB-01 | D88: Abuja | E88: WhatsApp | F88: Accessories | G88: Backpack | H88: C1150 | I88: Returning | J88: 3 | K88: 28000 | L88: 0.15 | M88: 71400 | N88: 16000 | O88: No | P88: Fatima | Q88: =COUNTIF($A$2:$A$433,A88)>1 -> FALSE | S88: =IF(M88<>J88*K88*(1-L88),"Mismatch","Match") -> Match | V88: =M88-(J88*N88) -> 23400 | W88: =J88*K88*(1-L88) -> 71400 | X88: =W88-(J88*N88) -> 23400 | Y88: =M88-(J88*N88) -> 23400
A89: 100088 | B89: 46191 | C89: KN-01 | D89: Kano | E89: WhatsApp | F89: Electronics | G89: Earbuds | H89: C1128 | I89: Returning | J89: 5 | K89: 32000 | L89: 0.05 | M89: 152000 | N89: 19000 | O89: Yes | P89: Chinedu | Q89: =COUNTIF($A$2:$A$433,A89)>1 -> FALSE | S89: =IF(M89<>J89*K89*(1-L89),"Mismatch","Match") -> Match | V89: =M89-(J89*N89) -> 57000 | W89: =J89*K89*(1-L89) -> 152000 | X89: =W89-(J89*N89) -> 57000 | Y89: =M89-(J89*N89) -> 57000
A90: 100089 | B90: 46024 | C90: KN-01 | D90: Kano | E90: In-store | F90: Home | G90: Blender | H90: C1089 | I90: Returning | J90: 1 | K90: 42000 | L90: 0.05 | M90: 39900 | N90: 28000 | O90: No | P90: Bola | Q90: =COUNTIF($A$2:$A$433,A90)>1 -> FALSE | S90: =IF(M90<>J90*K90*(1-L90),"Mismatch","Match") -> Match | V90: =M90-(J90*N90) -> 11900 | W90: =J90*K90*(1-L90) -> 39900 | X90: =W90-(J90*N90) -> 11900 | Y90: =M90-(J90*N90) -> 11900
A91: 100090 | B91: 46085 | C91: KN-01 | D91: Kano | E91: Online | F91: Home | G91: Blender | H91: C1169 | I91: Returning | J91: 4 | K91: 42000 | L91: 0.05 | M91: 159600 | N91: 28000 | O91: No | P91: Kemi | Q91: =COUNTIF($A$2:$A$433,A91)>1 -> FALSE | S91: =IF(M91<>J91*K91*(1-L91),"Mismatch","Match") -> Match | V91: =M91-(J91*N91) -> 47600 | W91: =J91*K91*(1-L91) -> 159600 | X91: =W91-(J91*N91) -> 47600 | Y91: =M91-(J91*N91) -> 47600
A92: 100091 | B92: 46190 | C92: PH-01 | D92: Port Harcourt | E92: Online | F92: Accessories | G92: Phone Case | H92: C1166 | I92: New | J92: 2 | K92: 9000 | L92: 0.1 | M92: 16200 | N92: 3500 | O92: No | P92: Grace | Q92: =COUNTIF($A$2:$A$433,A92)>1 -> FALSE | S92: =IF(M92<>J92*K92*(1-L92),"Mismatch","Match") -> Match | V92: =M92-(J92*N92) -> 9200 | W92: =J92*K92*(1-L92) -> 16200 | X92: =W92-(J92*N92) -> 9200 | Y92: =M92-(J92*N92) -> 9200
A93: 100092 | B93: 46153 | C93: PH-01 | D93: Port Harcourt | E93: In-store | F93: Home | G93: Blender | H93: C1108 | I93: Returning | J93: 4 | K93: 42000 | L93: 0.1 | M93: 166320 | N93: 28000 | O93: No | P93: Bola | Q93: =COUNTIF($A$2:$A$433,A93)>1 -> FALSE | S93: =IF(M93<>J93*K93*(1-L93),"Mismatch","Match") -> Mismatch | T93: =M93-(J93*K93*(1-L93)) -> 15120 | U93: =IF(AND(M93<>J93*K93*(1-L93),M93=J93*K93*(1-L93)*80%),"20% pattern","Other mismatch") -> Other mismatch | V93: =M93-(J93*N93) -> 54320 | W93: =J93*K93*(1-L93) -> 151200 | X93: =W93-(J93*N93) -> 39200 | Y93: =M93-(J93*N93) -> 54320
A94: 100093 | B94: 46139 | C94: AB-01 | D94: Abuja | E94: In-store | F94: Accessories | G94: Phone Case | H94: C1031 | I94: Returning | J94: 5 | K94: 9000 | L94: 0.2 | M94: 36000 | O94: No | P94: Fatima | Q94: {=IF(N94="",_xlfn.XLOOKUP(1,($G$2:$G$433=G94)*($N$2:$N$433<>""),$N$2:$N$433),"")} -> 3500 | S94: =IF(M94<>J94*K94*(1-L94),"Mismatch","Match") -> Match | V94: =M94-(J94*N94) -> 36000 | W94: =J94*K94*(1-L94) -> 36000 | X94: =W94-(J94*N94) -> 36000 | Y94: =M94-(J94*N94) -> 36000
A95: 100094 | B95: 46223 | C95: LG-02 | D95: Lagos | E95: In-store | F95: Home | G95: Blender | H95: C1036 | I95: Returning | J95: 4 | K95: 42000 | L95: 0.05 | M95: 127680 | N95: 28000 | O95: No | P95: Fatima | Q95: =COUNTIF($A$2:$A$433,A95)>1 -> FALSE | S95: =IF(M95<>J95*K95*(1-L95),"Mismatch","Match") -> Mismatch | T95: =M95-(J95*K95*(1-L95)) -> -31920 | U95: =IF(AND(M95<>J95*K95*(1-L95),M95=J95*K95*(1-L95)*80%),"20% pattern","Other mismatch") -> 20% pattern | V95: =M95-(J95*N95) -> 15680 | W95: =J95*K95*(1-L95) -> 159600 | X95: =W95-(J95*N95) -> 47600 | Y95: =M95-(J95*N95) -> 15680
A96: 100095 | B96: 46148 | C96: LG-01 | D96: Lagos | E96: Online | F96: Accessories | G96: Phone Case | H96: C1092 | I96: New | J96: 1 | K96: 9000 | L96: 0.05 | M96: 8550 | N96: 3500 | O96: No | P96: Aisha | Q96: =COUNTIF($A$2:$A$433,A96)>1 -> FALSE | S96: =IF(M96<>J96*K96*(1-L96),"Mismatch","Match") -> Match | V96: =M96-(J96*N96) -> 5050 | W96: =J96*K96*(1-L96) -> 8550 | X96: =W96-(J96*N96) -> 5050 | Y96: =M96-(J96*N96) -> 5050
A97: 100096 | B97: 46049 | C97: AB-02 | D97: Abuja | E97: Online | F97: Electronics | G97: Power Bank | H97: C1038 | I97: Returning | J97: 3 | K97: 26000 | L97: 0 | M97: 78000 | O97: No | P97: David | Q97: {=IF(N97="",_xlfn.XLOOKUP(1,($G$2:$G$433=G97)*($N$2:$N$433<>""),$N$2:$N$433),"")} -> 15000 | S97: =IF(M97<>J97*K97*(1-L97),"Mismatch","Match") -> Match | V97: =M97-(J97*N97) -> 78000 | W97: =J97*K97*(1-L97) -> 78000 | X97: =W97-(J97*N97) -> 78000 | Y97: =M97-(J97*N97) -> 78000
A98: 100097 | B98: 46122 | C98: PH-01 | D98: Port Harcourt | E98: In-store | F98: Electronics | G98: Power Bank | H98: C1134 | I98: Returning | J98: 4 | K98: 26000 | L98: 0 | M98: 104000 | N98: 15000 | O98: No | P98: Bola | Q98: =COUNTIF($A$2:$A$433,A98)>1 -> FALSE | S98: =IF(M98<>J98*K98*(1-L98),"Mismatch","Match") -> Match | V98: =M98-(J98*N98) -> 44000 | W98: =J98*K98*(1-L98) -> 104000 | X98: =W98-(J98*N98) -> 44000 | Y98: =M98-(J98*N98) -> 44000
A99: 100098 | B99: 46074 | C99: LG-01 | D99: Lagos | E99: Online | F99: Home | G99: Blender | H99: C1071 | I99: New | J99: 1 | K99: 42000 | L99: 0.05 | M99: 39900 | N99: 28000 | O99: No | P99: Fatima | Q99: =COUNTIF($A$2:$A$433,A99)>1 -> FALSE | S99: =IF(M99<>J99*K99*(1-L99),"Mismatch","Match") -> Match | V99: =M99-(J99*N99) -> 11900 | W99: =J99*K99*(1-L99) -> 39900 | X99: =W99-(J99*N99) -> 11900 | Y99: =M99-(J99*N99) -> 11900
A100: 100099 | B100: 46089 | C100: LG-01 | D100: Lagos | E100: In-store | F100: Electronics | G100: Earbuds | H100: C1111 | I100: New | J100: 2 | K100: 32000 | L100: 0 | M100: 64000 | N100: 19000 | O100: No | P100: Fatima | Q100: =COUNTIF($A$2:$A$433,A100)>1 -> FALSE | S100: =IF(M100<>J100*K100*(1-L100),"Mismatch","Match") -> Match | V100: =M100-(J100*N100) -> 26000 | W100: =J100*K100*(1-L100) -> 64000 | X100: =W100-(J100*N100) -> 26000 | Y100: =M100-(J100*N100) -> 26000
A101: 100100 | B101: 46086 | C101: LG-02 | D101: Lagos | E101: In-store | F101: Electronics | G101: Earbuds | H101: C1048 | I101: New | J101: 3 | K101: 32000 | L101: 0.05 | M101: 91200 | N101: 19000 | O101: No | P101: Ibrahim | Q101: =COUNTIF($A$2:$A$433,A101)>1 -> FALSE | S101: =IF(M101<>J101*K101*(1-L101),"Mismatch","Match") -> Match | V101: =M101-(J101*N101) -> 34200 | W101: =J101*K101*(1-L101) -> 91200 | X101: =W101-(J101*N101) -> 34200 | Y101: =M101-(J101*N101) -> 34200
A102: 100101 | B102: 46213 | C102: AB-02 | D102: Abuja | E102: In-store | F102: Accessories | G102: Phone Case | H102: C1052 | I102: Returning | J102: 5 | K102: 9000 | L102: 0.05 | M102: 42750 | N102: 3500 | O102: No | P102: Chinedu | Q102: =COUNTIF($A$2:$A$433,A102)>1 -> FALSE | S102: =IF(M102<>J102*K102*(1-L102),"Mismatch","Match") -> Match | V102: =M102-(J102*N102) -> 25250 | W102: =J102*K102*(1-L102) -> 42750 | X102: =W102-(J102*N102) -> 25250 | Y102: =M102-(J102*N102) -> 25250
A103: 100102 | B103: 46199 | C103: LG-02 | D103: Lagos | E103: WhatsApp | F103: Home | G103: Electric Kettle | H103: C1014 | I103: Returning | J103: 2 | K103: 24000 | L103: 0 | M103: 48000 | N103: 15000 | O103: No | P103: Ibrahim | Q103: =COUNTIF($A$2:$A$433,A103)>1 -> FALSE | S103: =IF(M103<>J103*K103*(1-L103),"Mismatch","Match") -> Match | V103: =M103-(J103*N103) -> 18000 | W103: =J103*K103*(1-L103) -> 48000 | X103: =W103-(J103*N103) -> 18000 | Y103: =M103-(J103*N103) -> 18000
A104: 100103 | B104: 46193 | C104: AB-01 | D104: Abuja | E104: Online | F104: Electronics | G104: Smartphone | H104: C1110 | I104: New | J104: 1 | K104: 165000 | L104: 0 | M104: 165000 | N104: 112000 | O104: Yes | P104: Bola | Q104: =COUNTIF($A$2:$A$433,A104)>1 -> FALSE | S104: =IF(M104<>J104*K104*(1-L104),"Mismatch","Match") -> Match | V104: =M104-(J104*N104) -> 53000 | W104: =J104*K104*(1-L104) -> 165000 | X104: =W104-(J104*N104) -> 53000 | Y104: =M104-(J104*N104) -> 53000
A105: 100104 | B105: 46066 | C105: LG-01 | D105: Lagos | E105: In-store | F105: Electronics | G105: Smartphone | H105: C1167 | I105: New | J105: 3 | K105: 165000 | L105: 0 | M105: 495000 | N105: 112000 | O105: No | P105: Grace | Q105: =COUNTIF($A$2:$A$433,A105)>1 -> FALSE | S105: =IF(M105<>J105*K105*(1-L105),"Mismatch","Match") -> Match | V105: =M105-(J105*N105) -> 159000 | W105: =J105*K105*(1-L105) -> 495000 | X105: =W105-(J105*N105) -> 159000 | Y105: =M105-(J105*N105) -> 159000
A106: 100105 | B106: 46177 | C106: IB-01 | D106: Ibadan | E106: WhatsApp | F106: Home | G106: Standing Fan | H106: C1002 | I106: New | J106: 2 | K106: 58000 | L106: 0 | M106: 116000 | N106: 39000 | O106: No | P106: David | Q106: =COUNTIF($A$2:$A$433,A106)>1 -> FALSE | S106: =IF(M106<>J106*K106*(1-L106),"Mismatch","Match") -> Match | V106: =M106-(J106*N106) -> 38000 | W106: =J106*K106*(1-L106) -> 116000 | X106: =W106-(J106*N106) -> 38000 | Y106: =M106-(J106*N106) -> 38000
A107: 100106 | B107: 46082 | C107: IB-01 | D107: Ibadan | E107: In-store | F107: Home | G107: Blender | H107: C1170 | I107: Returning | J107: 5 | K107: 42000 | L107: 0.05 | M107: 199500 | N107: 28000 | O107: No | P107: Kemi | Q107: =COUNTIF($A$2:$A$433,A107)>1 -> FALSE | S107: =IF(M107<>J107*K107*(1-L107),"Mismatch","Match") -> Match | V107: =M107-(J107*N107) -> 59500 | W107: =J107*K107*(1-L107) -> 199500 | X107: =W107-(J107*N107) -> 59500 | Y107: =M107-(J107*N107) -> 59500
A108: 100107 | B108: 46049 | C108: PH-01 | D108: Port Harcourt | E108: In-store | F108: Home | G108: Standing Fan | H108: C1082 | I108: Returning | J108: 1 | K108: 58000 | L108: 0.1 | M108: 52200 | N108: 39000 | O108: No | P108: Aisha | Q108: =COUNTIF($A$2:$A$433,A108)>1 -> FALSE | S108: =IF(M108<>J108*K108*(1-L108),"Mismatch","Match") -> Match | V108: =M108-(J108*N108) -> 13200 | W108: =J108*K108*(1-L108) -> 52200 | X108: =W108-(J108*N108) -> 13200 | Y108: =M108-(J108*N108) -> 13200
...
